Workbook

Sheet Instructions
A1: Skarion Manufacturing LLC - AR & Cash Application Practice Pack (January 2026)
A2: Purpose | B2: Use the 25 January 2026 customer invoices and the payment remittance batch to practice accounts receivable processing: sales invoicing, Virginia sales tax application, cash application, early-payment discounts, short-pay investigation, overpayment/credit memo handling, and AR aging.
A3: Student workflow | B3: 1) Review each invoice in the Customer Invoice Index. 2) For each line in the Payment Remittance Batch, compare Amount Received to the formula-driven Expected Amount Due. 3) Decide whether to apply the payment in full, flag a short pay for investigation, confirm a valid early-payment discount, or record a credit memo / refund for an overpayment. 4) Use the AR Aging Snapshot to confirm open customer balances tie out to total open receivables.
A4: Early-payment discount rule | B4: Terms of 2/10 Net 30 earn a 2% discount ONLY if payment is received within 10 days of the invoice date. If a customer deducts the discount after the 10-day window has closed, do not accept it as a valid discount - flag the shortfall as a short pay and follow up.
A5: Tax rule | B5: Virginia sales tax is 5.3% and applies only to taxable, tangible-goods invoices. Invoices marked Taxable = No are services and carry no sales tax. Do not recalculate tax on invoices already marked exempt.
A6: Short-pay rule | B6: If Amount Received is less than the Expected Amount Due and the shortfall is not an approved discount, treat it as a short pay. Investigate the cause (pricing dispute, damaged goods, deduction taken in error) before adjusting the customer's account.
A7: Overpayment rule | B7: If Amount Received is more than the Expected Amount Due, do not simply leave the credit balance sitting on the account. Confirm the amount with the customer, then record a credit memo or process a refund.
A8: Credit memo rule | B8: A credit memo reduces the amount owed on the specific invoice it is applied against. It is not a cash receipt and should never be entered as one.
A9: Instructor note | B9: The Instructor Key sheet contains the expected answer for every short-pay, overpayment, improper-discount, and valid-discount case in the Payment Remittance Batch. Hide or remove that sheet before giving the workbook to students if needed.

Sheet Customer Invoice Index
A1: Seq | B1: Invoice # | C1: Customer | D1: Customer ID | E1: Invoice Date | F1: Terms | G1: Due Date | H1: Taxable? | I1: Subtotal | J1: Sales Tax | K1: Invoice Total | L1: Product / Service Description | M1: Student AR Coding Decision | N1: Student Notes | P1: VA Sales Tax Rate | Q1: 0.053
A2: 1 | B2: SMI-2601-001 | C2: NOVA FiberBuild Contractors | D2: C-013 | E2: 46025 | F2: Net 30 | G2: =IF(F2="Net 15",E2+15,E2+30) -> 46055 | H2: Yes | I2: 15250 | J2: =IF(H2="Yes",ROUND(I2*$Q$1,2),0) -> 808.25 | K2: =I2+J2 -> 16058.25 | L2: Fiber conduit hanger and bracket hardware
A3: 2 | B3: SMI-2601-002 | C3: Hampton Roads Data Centers | D3: C-015 | E3: 46027 | F3: Net 45 | G3: =IF(F3="Net 15",E3+15,E3+30) -> 46057 | H3: No | I3: 22800 | J3: =IF(H3="Yes",ROUND(I3*$Q$1,2),0) -> 0 | K3: =I3+J3 -> 22800 | L3: On-site rack installation services
A4: 3 | B4: SMI-2601-003 | C4: Piedmont Electrical Group | D4: C-016 | E4: 46029 | F4: 2/10 Net 30 | G4: =IF(F4="Net 15",E4+15,E4+30) -> 46059 | H4: Yes | I4: 11600 | J4: =IF(H4="Yes",ROUND(I4*$Q$1,2),0) -> 614.8 | K4: =I4+J4 -> 12214.8 | L4: Electrical enclosure hardware order
A5: 4 | B5: SMI-2601-004 | C5: Metro DC Low Voltage | D5: C-017 | E5: 46030 | F5: Net 30 | G5: =IF(F5="Net 15",E5+15,E5+30) -> 46060 | H5: Yes | I5: 7950 | J5: =IF(H5="Yes",ROUND(I5*$Q$1,2),0) -> 421.35 | K5: =I5+J5 -> 8371.35 | L5: Low-voltage mounting hardware
A6: 5 | B6: SMI-2601-005 | C6: Richmond Metro Fiber | D6: C-018 | E6: 46032 | F6: Net 30 | G6: =IF(F6="Net 15",E6+15,E6+30) -> 46062 | H6: Yes | I6: 18400 | J6: =IF(H6="Yes",ROUND(I6*$Q$1,2),0) -> 975.2 | K6: =I6+J6 -> 19375.2 | L6: Fiber vault hardware kit
A7: 6 | B7: SMI-2601-006 | C7: Dulles Cloud Campus LLC | D7: C-019 | E7: 46034 | F7: Net 45 | G7: =IF(F7="Net 15",E7+15,E7+30) -> 46064 | H7: No | I7: 25500 | J7: =IF(H7="Yes",ROUND(I7*$Q$1,2),0) -> 0 | K7: =I7+J7 -> 25500 | L7: Data center build-out consulting services
A8: 7 | B8: SMI-2601-007 | C8: Coastal Electric & Controls | D8: C-014 | E8: 46039 | F8: 2/10 Net 30 | G8: =IF(F8="Net 15",E8+15,E8+30) -> 46069 | H8: Yes | I8: 9200 | J8: =IF(H8="Yes",ROUND(I8*$Q$1,2),0) -> 487.6 | K8: =I8+J8 -> 9687.6 | L8: Control panel hardware order
A9: 8 | B9: SMI-2601-008 | C9: Cavalier Controls Inc. | D9: C-020 | E9: 46040 | F9: Net 30 | G9: =IF(F9="Net 15",E9+15,E9+30) -> 46070 | H9: Yes | I9: 13750 | J9: =IF(H9="Yes",ROUND(I9*$Q$1,2),0) -> 728.75 | K9: =I9+J9 -> 14478.75 | L9: Panel mounting hardware
A10: 9 | B10: SMI-2601-009 | C10: Shenandoah Energy Services | D10: C-021 | E10: 46042 | F10: Net 45 | G10: =IF(F10="Net 15",E10+15,E10+30) -> 46072 | H10: No | I10: 16100 | J10: =IF(H10="Yes",ROUND(I10*$Q$1,2),0) -> 0 | K10: =I10+J10 -> 16100 | L10: Field engineering services
A11: 10 | B11: SMI-2601-010 | C11: Patriot Network Solutions | D11: C-022 | E11: 46044 | F11: Net 30 | G11: =IF(F11="Net 15",E11+15,E11+30) -> 46074 | H11: Yes | I11: 8600 | J11: =IF(H11="Yes",ROUND(I11*$Q$1,2),0) -> 455.8 | K11: =I11+J11 -> 9055.8 | L11: Network cabinet hardware
A12: 11 | B12: SMI-2601-011 | C12: Chesapeake Municipal Works | D12: C-023 | E12: 46047 | F12: Net 45 | G12: =IF(F12="Net 15",E12+15,E12+30) -> 46077 | H12: No | I12: 10250 | J12: =IF(H12="Yes",ROUND(I12*$Q$1,2),0) -> 0 | K12: =I12+J12 -> 10250 | L12: Municipal facility consulting services
A13: 12 | B13: SMI-2601-012 | C13: Manassas Telecom Services | D13: C-024 | E13: 46049 | F13: Net 30 | G13: =IF(F13="Net 15",E13+15,E13+30) -> 46079 | H13: Yes | I13: 6780 | J13: =IF(H13="Yes",ROUND(I13*$Q$1,2),0) -> 359.34 | K13: =I13+J13 -> 7139.34 | L13: Telecom enclosure hardware
... A26: 25 | B26: SMI-2601-025 | C26: NOVA FiberBuild Contractors | D26: C-013 | E26: 46052 | F26: Net 30 | G26: =IF(F26="Net 15",E26+15,E26+30) -> 46082 | H26: Yes | I26: 11900 | J26: =IF(H26="Yes",ROUND(I26*$Q$1,2),0) -> 630.7 | K26: =I26+J26 -> 12530.7 | L26: Fiber conduit mounting hardware, second order
H27: TOTALS | I27: =SUM(I2:I26) -> 324980 | J27: =SUM(J2:J26) -> 11428.39 | K27: =SUM(K2:K26) -> 336408.39

Sheet Payment Remittance Batch
A1: Seq | B1: Payment Date | C1: Customer | D1: Customer ID | E1: Invoice Applied | F1: Invoice Date | G1: Terms | H1: Subtotal | I1: Invoice Total | J1: Days to Pay | K1: Discount Eligible? | L1: Discount Amount | M1: Credit Memo Applied | N1: Expected Amount Due | O1: Amount Received | P1: Variance | Q1: Student Action Required | R1: Student Notes
A2: 1 | B2: 46034 | C2: =INDEX('Customer Invoice Index'!$C$2:$C$26,MATCH(E2,'Customer Invoice Index'!$B$2:$B$26,0)) -> Piedmont Electrical Group | D2: =INDEX('Customer Invoice Index'!$D$2:$D$26,MATCH(E2,'Customer Invoice Index'!$B$2:$B$26,0)) -> C-016 | E2: SMI-2601-003 | F2: =INDEX('Customer Invoice Index'!$E$2:$E$26,MATCH(E2,'Customer Invoice Index'!$B$2:$B$26,0)) -> 46029 | G2: =INDEX('Customer Invoice Index'!$F$2:$F$26,MATCH(E2,'Customer Invoice Index'!$B$2:$B$26,0)) -> 2/10 Net 30 | H2: =INDEX('Customer Invoice Index'!$I$2:$I$26,MATCH(E2,'Customer Invoice Index'!$B$2:$B$26,0)) -> 11600 | I2: =INDEX('Customer Invoice Index'!$K$2:$K$26,MATCH(E2,'Customer Invoice Index'!$B$2:$B$26,0)) -> 12214.8 | J2: =B2-F2 -> 5 | K2: =IF(AND(G2="2/10 Net 30",J2<=10),"Yes","No") -> Yes | L2: =IF(K2="Yes",ROUND(H2*0.02,2),0) -> 232 | M2: 0 | N2: =I2-L2-M2 -> 11982.8 | O2: 11982.8 | P2: =O2-N2 -> 0 | R2: Discount taken correctly
A3: 2 | B3: 46037 | C3: =INDEX('Customer Invoice Index'!$C$2:$C$26,MATCH(E3,'Customer Invoice Index'!$B$2:$B$26,0)) -> Metro DC Low Voltage | D3: =INDEX('Customer Invoice Index'!$D$2:$D$26,MATCH(E3,'Customer Invoice Index'!$B$2:$B$26,0)) -> C-017 | E3: SMI-2601-004 | F3: =INDEX('Customer Invoice Index'!$E$2:$E$26,MATCH(E3,'Customer Invoice Index'!$B$2:$B$26,0)) -> 46030 | G3: =INDEX('Customer Invoice Index'!$F$2:$F$26,MATCH(E3,'Customer Invoice Index'!$B$2:$B$26,0)) -> Net 30 | H3: =INDEX('Customer Invoice Index'!$I$2:$I$26,MATCH(E3,'Customer Invoice Index'!$B$2:$B$26,0)) -> 7950 | I3: =INDEX('Customer Invoice Index'!$K$2:$K$26,MATCH(E3,'Customer Invoice Index'!$B$2:$B$26,0)) -> 8371.35 | J3: =B3-F3 -> 7 | K3: =IF(AND(G3="2/10 Net 30",J3<=10),"Yes","No") -> No | L3: =IF(K3="Yes",ROUND(H3*0.02,2),0) -> 0 | M3: 0 | N3: =I3-L3-M3 -> 8371.35 | O3: 8371.35 | P3: =O3-N3 -> 0 | R3: Full payment, on time
A4: 3 | B4: 46047 | C4: =INDEX('Customer Invoice Index'!$C$2:$C$26,MATCH(E4,'Customer Invoice Index'!$B$2:$B$26,0)) -> NOVA FiberBuild Contractors | D4: =INDEX('Customer Invoice Index'!$D$2:$D$26,MATCH(E4,'Customer Invoice Index'!$B$2:$B$26,0)) -> C-013 | E4: SMI-2601-001 | F4: =INDEX('Customer Invoice Index'!$E$2:$E$26,MATCH(E4,'Customer Invoice Index'!$B$2:$B$26,0)) -> 46025 | G4: =INDEX('Customer Invoice Index'!$F$2:$F$26,MATCH(E4,'Customer Invoice Index'!$B$2:$B$26,0)) -> Net 30 | H4: =INDEX('Customer Invoice Index'!$I$2:$I$26,MATCH(E4,'Customer Invoice Index'!$B$2:$B$26,0)) -> 15250 | I4: =INDEX('Customer Invoice Index'!$K$2:$K$26,MATCH(E4,'Customer Invoice Index'!$B$2:$B$26,0)) -> 16058.25 | J4: =B4-F4 -> 22 | K4: =IF(AND(G4="2/10 Net 30",J4<=10),"Yes","No") -> No | L4: =IF(K4="Yes",ROUND(H4*0.02,2),0) -> 0 | M4: 0 | N4: =I4-L4-M4 -> 16058.25 | O4: 8000 | P4: =O4-N4 -> -8058.25 | R4: SHORT PAY - partial, customer disputes balance
A5: 4 | B5: 46049 | C5: =INDEX('Customer Invoice Index'!$C$2:$C$26,MATCH(E5,'Customer Invoice Index'!$B$2:$B$26,0)) -> Coastal Electric & Controls | D5: =INDEX('Customer Invoice Index'!$D$2:$D$26,MATCH(E5,'Customer Invoice Index'!$B$2:$B$26,0)) -> C-014 | E5: SMI-2601-007 | F5: =INDEX('Customer Invoice Index'!$E$2:$E$26,MATCH(E5,'Customer Invoice Index'!$B$2:$B$26,0)) -> 46039 | G5: =INDEX('Customer Invoice Index'!$F$2:$F$26,MATCH(E5,'Customer Invoice Index'!$B$2:$B$26,0)) -> 2/10 Net 30 | H5: =INDEX('Customer Invoice Index'!$I$2:$I$26,MATCH(E5,'Customer Invoice Index'!$B$2:$B$26,0)) -> 9200 | I5: =INDEX('Customer Invoice Index'!$K$2:$K$26,MATCH(E5,'Customer Invoice Index'!$B$2:$B$26,0)) -> 9687.6 | J5: =B5-F5 -> 10 | K5: =IF(AND(G5="2/10 Net 30",J5<=10),"Yes","No") -> Yes | L5: =IF(K5="Yes",ROUND(H5*0.02,2),0) -> 184 | M5: 0 | N5: =I5-L5-M5 -> 9503.6 | O5: 9503.6 | P5: =O5-N5 -> 0 | R5: Discount taken correctly
A6: 5 | B6: 46053 | C6: =INDEX('Customer Invoice Index'!$C$2:$C$26,MATCH(E6,'Customer Invoice Index'!$B$2:$B$26,0)) -> Patriot Network Solutions | D6: =INDEX('Customer Invoice Index'!$D$2:$D$26,MATCH(E6,'Customer Invoice Index'!$B$2:$B$26,0)) -> C-022 | E6: SMI-2601-010 | F6: =INDEX('Customer Invoice Index'!$E$2:$E$26,MATCH(E6,'Customer Invoice Index'!$B$2:$B$26,0)) -> 46044 | G6: =INDEX('Customer Invoice Index'!$F$2:$F$26,MATCH(E6,'Customer Invoice Index'!$B$2:$B$26,0)) -> Net 30 | H6: =INDEX('Customer Invoice Index'!$I$2:$I$26,MATCH(E6,'Customer Invoice Index'!$B$2:$B$26,0)) -> 8600 | I6: =INDEX('Customer Invoice Index'!$K$2:$K$26,MATCH(E6,'Customer Invoice Index'!$B$2:$B$26,0)) -> 9055.8 | J6: =B6-F6 -> 9 | K6: =IF(AND(G6="2/10 Net 30",J6<=10),"Yes","No") -> No | L6: =IF(K6="Yes",ROUND(H6*0.02,2),0) -> 0 | M6: 0 | N6: =I6-L6-M6 -> 9055.8 | O6: 9000 | P6: =O6-N6 -> -55.8 | R6: SHORT PAY - small variance
A7: 6 | B7: 46053 | C7: =INDEX('Customer Invoice Index'!$C$2:$C$26,MATCH(E7,'Customer Invoice Index'!$B$2:$B$26,0)) -> Manassas Telecom Services | D7: =INDEX('Customer Invoice Index'!$D$2:$D$26,MATCH(E7,'Customer Invoice Index'!$B$2:$B$26,0)) -> C-024 | E7: SMI-2601-012 | F7: =INDEX('Customer Invoice Index'!$E$2:$E$26,MATCH(E7,'Customer Invoice Index'!$B$2:$B$26,0)) -> 46049 | G7: =INDEX('Customer Invoice Index'!$F$2:$F$26,MATCH(E7,'Customer Invoice Index'!$B$2:$B$26,0)) -> Net 30 | H7: =INDEX('Customer Invoice Index'!$I$2:$I$26,MATCH(E7,'Customer Invoice Index'!$B$2:$B$26,0)) -> 6780 | I7: =INDEX('Customer Invoice Index'!$K$2:$K$26,MATCH(E7,'Customer Invoice Index'!$B$2:$B$26,0)) -> 7139.34 | J7: =B7-F7 -> 4 | K7: =IF(AND(G7="2/10 Net 30",J7<=10),"Yes","No") -> No | L7: =IF(K7="Yes",ROUND(H7*0.02,2),0) -> 0 | M7: 526.5 | N7: =I7-L7-M7 -> 6612.84 | O7: 6612.84 | P7: =O7-N7 -> 0 | R7: Paid after credit memo CM-2601-001 applied
A8: 7 | B8: 46036 | C8: =INDEX('Customer Invoice Index'!$C$2:$C$26,MATCH(E8,'Customer Invoice Index'!$B$2:$B$26,0)) -> Blue Ridge Retail Fixtures | D8: =INDEX('Customer Invoice Index'!$D$2:$D$26,MATCH(E8,'Customer Invoice Index'!$B$2:$B$26,0)) -> C-001 | E8: SMI-2601-013 | F8: =INDEX('Customer Invoice Index'!$E$2:$E$26,MATCH(E8,'Customer Invoice Index'!$B$2:$B$26,0)) -> 46026 | G8: =INDEX('Customer Invoice Index'!$F$2:$F$26,MATCH(E8,'Customer Invoice Index'!$B$2:$B$26,0)) -> Net 30 | H8: =INDEX('Customer Invoice Index'!$I$2:$I$26,MATCH(E8,'Customer Invoice Index'!$B$2:$B$26,0)) -> 9800 | I8: =INDEX('Customer Invoice Index'!$K$2:$K$26,MATCH(E8,'Customer Invoice Index'!$B$2:$B$26,0)) -> 10319.4 | J8: =B8-F8 -> 10 | K8: =IF(AND(G8="2/10 Net 30",J8<=10),"Yes","No") -> No | L8: =IF(K8="Yes",ROUND(H8*0.02,2),0) -> 0 | M8: 0 | N8: =I8-L8-M8 -> 10319.4 | O8: 10500 | P8: =O8-N8 -> 180.6 | R8: OVERPAYMENT
A9: 8 | B9: 46036 | C9: =INDEX('Customer Invoice Index'!$C$2:$C$26,MATCH(E9,'Customer Invoice Index'!$B$2:$B$26,0)) -> Shenandoah Builders | D9: =INDEX('Customer Invoice Index'!$D$2:$D$26,MATCH(E9,'Customer Invoice Index'!$B$2:$B$26,0)) -> C-002 | E9: SMI-2601-014 | F9: =INDEX('Customer Invoice Index'!$E$2:$E$26,MATCH(E9,'Customer Invoice Index'!$B$2:$B$26,0)) -> 46028 | G9: =INDEX('Customer Invoice Index'!$F$2:$F$26,MATCH(E9,'Customer Invoice Index'!$B$2:$B$26,0)) -> 2/10 Net 30 | H9: =INDEX('Customer Invoice Index'!$I$2:$I$26,MATCH(E9,'Customer Invoice Index'!$B$2:$B$26,0)) -> 14200 | I9: =INDEX('Customer Invoice Index'!$K$2:$K$26,MATCH(E9,'Customer Invoice Index'!$B$2:$B$26,0)) -> 14952.6 | J9: =B9-F9 -> 8 | K9: =IF(AND(G9="2/10 Net 30",J9<=10),"Yes","No") -> Yes | L9: =IF(K9="Yes",ROUND(H9*0.02,2),0) -> 284 | M9: 0 | N9: =I9-L9-M9 -> 14668.6 | O9: 14668.6 | P9: =O9-N9 -> 0 | R9: Discount taken correctly
A10: 9 | B10: 46052 | C10: =INDEX('Customer Invoice Index'!$C$2:$C$26,MATCH(E10,'Customer Invoice Index'!$B$2:$B$26,0)) -> Old Dominion Components | D10: =INDEX('Customer Invoice Index'!$D$2:$D$26,MATCH(E10,'Customer Invoice Index'!$B$2:$B$26,0)) -> C-006 | E10: SMI-2601-018 | F10: =INDEX('Customer Invoice Index'!$E$2:$E$26,MATCH(E10,'Customer Invoice Index'!$B$2:$B$26,0)) -> 46036 | G10: =INDEX('Customer Invoice Index'!$F$2:$F$26,MATCH(E10,'Customer Invoice Index'!$B$2:$B$26,0)) -> 2/10 Net 30 | H10: =INDEX('Customer Invoice Index'!$I$2:$I$26,MATCH(E10,'Customer Invoice Index'!$B$2:$B$26,0)) -> 8300 | I10: =INDEX('Customer Invoice Index'!$K$2:$K$26,MATCH(E10,'Customer Invoice Index'!$B$2:$B$26,0)) -> 8739.9 | J10: =B10-F10 -> 16 | K10: =IF(AND(G10="2/10 Net 30",J10<=10),"Yes","No") -> No | L10: =IF(K10="Yes",ROUND(H10*0.02,2),0) -> 0 | M10: 0 | N10: =I10-L10-M10 -> 8739.9 | O10: 8573.9 | P10: =O10-N10 -> -166 | R10: IMPROPER DISCOUNT - paid outside 10-day window but deducted 2% anyway
A11: 10 | B11: 46052 | C11: =INDEX('Customer Invoice Index'!$C$2:$C$26,MATCH(E11,'Customer Invoice Index'!$B$2:$B$26,0)) -> Appalachian Retail Group | D11: =INDEX('Customer Invoice Index'!$D$2:$D$26,MATCH(E11,'Customer Invoice Index'!$B$2:$B$26,0)) -> C-011 | E11: SMI-2601-023 | F11: =INDEX('Customer Invoice Index'!$E$2:$E$26,MATCH(E11,'Customer Invoice Index'!$B$2:$B$26,0)) -> 46046 | G11: =INDEX('Customer Invoice Index'!$F$2:$F$26,MATCH(E11,'Customer Invoice Index'!$B$2:$B$26,0)) -> 2/10 Net 30 | H11: =INDEX('Customer Invoice Index'!$I$2:$I$26,MATCH(E11,'Customer Invoice Index'!$B$2:$B$26,0)) -> 7600 | I11: =INDEX('Customer Invoice Index'!$K$2:$K$26,MATCH(E11,'Customer Invoice Index'!$B$2:$B$26,0)) -> 8002.8 | J11: =B11-F11 -> 6 | K11: =IF(AND(G11="2/10 Net 30",J11<=10),"Yes","No") -> Yes | L11: =IF(K11="Yes",ROUND(H11*0.02,2),0) -> 152 | M11: 0 | N11: =I11-L11-M11 -> 7850.8 | O11: 7850.8 | P11: =O11-N11 -> 0 | R11: Discount taken correctly
A12: 11 | B12: 46051 | C12: =INDEX('Customer Invoice Index'!$C$2:$C$26,MATCH(E12,'Customer Invoice Index'!$B$2:$B$26,0)) -> Virginia Transit Parts | D12: =INDEX('Customer Invoice Index'!$D$2:$D$26,MATCH(E12,'Customer Invoice Index'!$B$2:$B$26,0)) -> C-010 | E12: SMI-2601-022 | F12: =INDEX('Customer Invoice Index'!$E$2:$E$26,MATCH(E12,'Customer Invoice Index'!$B$2:$B$26,0)) -> 46045 | G12: =INDEX('Customer Invoice Index'!$F$2:$F$26,MATCH(E12,'Customer Invoice Index'!$B$2:$B$26,0)) -> Net 30 | H12: =INDEX('Customer Invoice Index'!$I$2:$I$26,MATCH(E12,'Customer Invoice Index'!$B$2:$B$26,0)) -> 10750 | I12: =INDEX('Customer Invoice Index'!$K$2:$K$26,MATCH(E12,'Customer Invoice Index'!$B$2:$B$26,0)) -> 11319.75 | J12: =B12-F12 -> 6 | K12: =IF(AND(G12="2/10 Net 30",J12<=10),"Yes","No") -> No | L12: =IF(K12="Yes",ROUND(H12*0.02,2),0) -> 0 | M12: 0 | N12: =I12-L12-M12 -> 11319.75 | O12: 10800 | P12: =O12-N12 -> -519.75 | R12: SHORT PAY - damaged parts dispute
A13: 12 | B13: 46040 | C13: =INDEX('Customer Invoice Index'!$C$2:$C$26,MATCH(E13,'Customer Invoice Index'!$B$2:$B$26,0)) -> Hampton Roads Data Centers | D13: =INDEX('Customer Invoice Index'!$D$2:$D$26,MATCH(E13,'Customer Invoice Index'!$B$2:$B$26,0)) -> C-015 | E13: SMI-2601-002 | F13: =INDEX('Customer Invoice Index'!$E$2:$E$26,MATCH(E13,'Customer Invoice Index'!$B$2:$B$26,0)) -> 46027 | G13: =INDEX('Customer Invoice Index'!$F$2:$F$26,MATCH(E13,'Customer Invoice Index'!$B$2:$B$26,0)) -> Net 45 | H13: =INDEX('Customer Invoice Index'!$I$2:$I$26,MATCH(E13,'Customer Invoice Index'!$B$2:$B$26,0)) -> 22800 | I13: =INDEX('Customer Invoice Index'!$K$2:$K$26,MATCH(E13,'Customer Invoice Index'!$B$2:$B$26,0)) -> 22800 | J13: =B13-F13 -> 13 | K13: =IF(AND(G13="2/10 Net 30",J13<=10),"Yes","No") -> No | L13: =IF(K13="Yes",ROUND(H13*0.02,2),0) -> 0 | M13: 0 | N13: =I13-L13-M13 -> 22800 | O13: 22800 | P13: =O13-N13 -> 0 | R13: Full payment, on time
... A21: 20 | B21: 46053 | C21: =INDEX('Customer Invoice Index'!$C$2:$C$26,MATCH(E21,'Customer Invoice Index'!$B$2:$B$26,0)) -> Chesapeake Fabricators | D21: =INDEX('Customer Invoice Index'!$D$2:$D$26,MATCH(E21,'Customer Invoice Index'!$B$2:$B$26,0)) -> C-012 | E21: SMI-2601-024 | F21: =INDEX('Customer Invoice Index'!$E$2:$E$26,MATCH(E21,'Customer Invoice Index'!$B$2:$B$26,0)) -> 46050 | G21: =INDEX('Customer Invoice Index'!$F$2:$F$26,MATCH(E21,'Customer Invoice Index'!$B$2:$B$26,0)) -> Net 30 | H21: =INDEX('Customer Invoice Index'!$I$2:$I$26,MATCH(E21,'Customer Invoice Index'!$B$2:$B$26,0)) -> 13400 | I21: =INDEX('Customer Invoice Index'!$K$2:$K$26,MATCH(E21,'Customer Invoice Index'!$B$2:$B$26,0)) -> 13400 | J21: =B21-F21 -> 3 | K21: =IF(AND(G21="2/10 Net 30",J21<=10),"Yes","No") -> No | L21: =IF(K21="Yes",ROUND(H21*0.02,2),0) -> 0 | M21: 0 | N21: =I21-L21-M21 -> 13400 | O21: 13400 | P21: =O21-N21 -> 0 | R21: Full payment, on time
N22: TOTALS | O22: =SUM(O2:O21) -> 243444.54 | P22: =SUM(P2:P21) -> -8619.2

Sheet Instructor Key
A1: Seq | B1: Customer | C1: Invoice Applied | D1: Invoice Total | E1: Issue Type | F1: Expected Student Action | G1: Expected Amount Due | H1: Amount Received | I1: Variance | J1: Notes
A2: 1 | B2: Piedmont Electrical Group | C2: SMI-2601-003 | D2: 12214.8 | E2: Valid early-payment discount | F2: No action needed. Payment received 5 days after invoice, within the 10-day window. Apply the $232.00 discount and close the invoice. | G2: 11982.8 | H2: 11982.8 | I2: 0 | J2: 2% of $11,600.00 subtotal = $232.00; tax is not discounted.
A3: 2 | B3: Coastal Electric & Controls | C3: SMI-2601-007 | D3: 9687.6 | E3: Valid early-payment discount | F3: No action needed. Payment received on day 10, within the window. Apply the $184.00 discount and close the invoice. | G3: 9503.6 | H3: 9503.6 | I3: 0 | J3: 2% of $9,200.00 subtotal = $184.00.
A4: 3 | B4: Shenandoah Builders | C4: SMI-2601-014 | D4: 14952.6 | E4: Valid early-payment discount | F4: No action needed. Payment received 8 days after invoice, within the window. Apply the $284.00 discount and close the invoice. | G4: 14668.6 | H4: 14668.6 | I4: 0 | J4: 2% of $14,200.00 subtotal = $284.00.
A5: 4 | B5: Appalachian Retail Group | C5: SMI-2601-023 | D5: 8002.8 | E5: Valid early-payment discount | F5: No action needed. Payment received 6 days after invoice, within the window. Apply the $152.00 discount and close the invoice. | G5: 7850.8 | H5: 7850.8 | I5: 0 | J5: 2% of $7,600.00 subtotal = $152.00.
A6: 5 | B6: Old Dominion Components | C6: SMI-2601-018 | D6: 8739.9 | E6: Improper discount taken | F6: Do not accept the deduction. Payment arrived 16 days after the invoice, outside the 10-day window, so the $166.00 discount was not earned. Bill the customer for the $166.00 difference. | G6: 8739.9 | H6: 8573.9 | I6: -166 | J6: 2/10 Net 30 terms; customer took the 2% discount late.
A7: 6 | B7: NOVA FiberBuild Contractors | C7: SMI-2601-001 | D7: 16058.25 | E7: Short pay - disputed balance | F7: Investigate before adjusting the account. Contact the customer about the $8,058.25 unpaid balance; do not write it off without a documented reason. | G7: 16058.25 | H7: 8000 | I7: -8058.25 | J7: Customer sent a partial payment with no discount terms on this invoice; reason for the shortfall is undocumented.
A8: 7 | B8: Patriot Network Solutions | C8: SMI-2601-010 | D8: 9055.8 | E8: Short pay - small variance | F8: Investigate before adjusting the account. Contact the customer about the $55.80 shortfall; likely a minor billing dispute or rounding error on their end. | G8: 9055.8 | H8: 9000 | I8: -55.8 | J8: No discount terms apply to this Net 30 invoice.
A9: 8 | B9: Virginia Transit Parts | C9: SMI-2601-022 | D9: 11319.75 | E9: Short pay - damaged goods dispute | F9: Investigate before adjusting the account. Customer is disputing $519.75 of the invoice for damaged parts; request documentation (photos, RMA) before issuing any credit. | G9: 11319.75 | H9: 10800 | I9: -519.75 | J9: No discount terms apply to this Net 30 invoice.
A10: 9 | B10: Blue Ridge Retail Fixtures | C10: SMI-2601-013 | D10: 10319.4 | E10: Overpayment | F10: Confirm the overpayment with the customer, then record a credit memo for $180.60 or process a refund. Do not leave the credit balance unresolved on the account. | G10: 10319.4 | H10: 10500 | I10: 180.6 | J10: Customer remitted $180.60 more than the invoice total; cause unconfirmed.

Sheet AR Aging Snapshot
A1: AR Aging Snapshot - As of January 31, 2026
A3: As-of Date | B3: 46053
A5: Note: this snapshot covers only the 25 invoices in the Customer Invoice Index below (Jan 2026). Opening AR carried from December is tracked separately in the Module 03 Practice Exercise and is not included here, so every open balance is 30 days old or newer.
A7: Aging Bucket | B7: Open AR Amount
A8: Current (0-30 days) | B8: =SUMIF($I$17:$I$41,A8,$G$17:$G$41) -> 92437.35
A9: 31-60 days | B9: =SUMIF($I$17:$I$41,A9,$G$17:$G$41) -> 0
A10: 61-90 days | B10: =SUMIF($I$17:$I$41,A10,$G$17:$G$41) -> 0
A11: 90+ days | B11: =SUMIF($I$17:$I$41,A11,$G$17:$G$41) -> 0
A12: Total Open AR | B12: =SUM(B8:B11) -> 92437.35
A13: Tie-out check (Summary = Detail) | B13: =IF(ROUND(B12-SUM($G$17:$G$41),2)=0,"TIE","OUT OF BALANCE") -> TIE
A16: Seq | B16: Invoice # | C16: Customer | D16: Invoice Date | E16: Invoice Total | F16: Amount Applied (Cash + Credit Memo) | G16: Open Balance | H16: Days Outstanding | I16: Aging Bucket
A17: 1 | B17: SMI-2601-001 | C17: =INDEX('Customer Invoice Index'!$C$2:$C$26,MATCH(B17,'Customer Invoice Index'!$B$2:$B$26,0)) -> NOVA FiberBuild Contractors | D17: =INDEX('Customer Invoice Index'!$E$2:$E$26,MATCH(B17,'Customer Invoice Index'!$B$2:$B$26,0)) -> 46025 | E17: =INDEX('Customer Invoice Index'!$K$2:$K$26,MATCH(B17,'Customer Invoice Index'!$B$2:$B$26,0)) -> 16058.25 | F17: =SUMIFS('Payment Remittance Batch'!$O$2:$O$21,'Payment Remittance Batch'!$E$2:$E$21,B17)+SUMIFS('Payment Remittance Batch'!$M$2:$M$21,'Payment Remittance Batch'!$E$2:$E$21,B17) -> 8000 | G17: =E17-F17 -> 8058.25 | H17: =$B$3-D17 -> 28 | I17: =IF(ROUND(G17,2)=0,"Paid in Full",IF(H17<=30,"Current (0-30 days)",IF(H17<=60,"31-60 days",IF(H17<=90,"61-90 days","90+ days")))) -> Current (0-30 days)
A18: 2 | B18: SMI-2601-002 | C18: =INDEX('Customer Invoice Index'!$C$2:$C$26,MATCH(B18,'Customer Invoice Index'!$B$2:$B$26,0)) -> Hampton Roads Data Centers | D18: =INDEX('Customer Invoice Index'!$E$2:$E$26,MATCH(B18,'Customer Invoice Index'!$B$2:$B$26,0)) -> 46027 | E18: =INDEX('Customer Invoice Index'!$K$2:$K$26,MATCH(B18,'Customer Invoice Index'!$B$2:$B$26,0)) -> 22800 | F18: =SUMIFS('Payment Remittance Batch'!$O$2:$O$21,'Payment Remittance Batch'!$E$2:$E$21,B18)+SUMIFS('Payment Remittance Batch'!$M$2:$M$21,'Payment Remittance Batch'!$E$2:$E$21,B18) -> 22800 | G18: =E18-F18 -> 0 | H18: =$B$3-D18 -> 26 | I18: =IF(ROUND(G18,2)=0,"Paid in Full",IF(H18<=30,"Current (0-30 days)",IF(H18<=60,"31-60 days",IF(H18<=90,"61-90 days","90+ days")))) -> Paid in Full
A19: 3 | B19: SMI-2601-003 | C19: =INDEX('Customer Invoice Index'!$C$2:$C$26,MATCH(B19,'Customer Invoice Index'!$B$2:$B$26,0)) -> Piedmont Electrical Group | D19: =INDEX('Customer Invoice Index'!$E$2:$E$26,MATCH(B19,'Customer Invoice Index'!$B$2:$B$26,0)) -> 46029 | E19: =INDEX('Customer Invoice Index'!$K$2:$K$26,MATCH(B19,'Customer Invoice Index'!$B$2:$B$26,0)) -> 12214.8 | F19: =SUMIFS('Payment Remittance Batch'!$O$2:$O$21,'Payment Remittance Batch'!$E$2:$E$21,B19)+SUMIFS('Payment Remittance Batch'!$M$2:$M$21,'Payment Remittance Batch'!$E$2:$E$21,B19) -> 11982.8 | G19: =E19-F19 -> 232 | H19: =$B$3-D19 -> 24 | I19: =IF(ROUND(G19,2)=0,"Paid in Full",IF(H19<=30,"Current (0-30 days)",IF(H19<=60,"31-60 days",IF(H19<=90,"61-90 days","90+ days")))) -> Current (0-30 days)
A20: 4 | B20: SMI-2601-004 | C20: =INDEX('Customer Invoice Index'!$C$2:$C$26,MATCH(B20,'Customer Invoice Index'!$B$2:$B$26,0)) -> Metro DC Low Voltage | D20: =INDEX('Customer Invoice Index'!$E$2:$E$26,MATCH(B20,'Customer Invoice Index'!$B$2:$B$26,0)) -> 46030 | E20: =INDEX('Customer Invoice Index'!$K$2:$K$26,MATCH(B20,'Customer Invoice Index'!$B$2:$B$26,0)) -> 8371.35 | F20: =SUMIFS('Payment Remittance Batch'!$O$2:$O$21,'Payment Remittance Batch'!$E$2:$E$21,B20)+SUMIFS('Payment Remittance Batch'!$M$2:$M$21,'Payment Remittance Batch'!$E$2:$E$21,B20) -> 8371.35 | G20: =E20-F20 -> 0 | H20: =$B$3-D20 -> 23 | I20: =IF(ROUND(G20,2)=0,"Paid in Full",IF(H20<=30,"Current (0-30 days)",IF(H20<=60,"31-60 days",IF(H20<=90,"61-90 days","90+ days")))) -> Paid in Full
A21: 5 | B21: SMI-2601-005 | C21: =INDEX('Customer Invoice Index'!$C$2:$C$26,MATCH(B21,'Customer Invoice Index'!$B$2:$B$26,0)) -> Richmond Metro Fiber | D21: =INDEX('Customer Invoice Index'!$E$2:$E$26,MATCH(B21,'Customer Invoice Index'!$B$2:$B$26,0)) -> 46032 | E21: =INDEX('Customer Invoice Index'!$K$2:$K$26,MATCH(B21,'Customer Invoice Index'!$B$2:$B$26,0)) -> 19375.2 | F21: =SUMIFS('Payment Remittance Batch'!$O$2:$O$21,'Payment Remittance Batch'!$E$2:$E$21,B21)+SUMIFS('Payment Remittance Batch'!$M$2:$M$21,'Payment Remittance Batch'!$E$2:$E$21,B21) -> 19375.2 | G21: =E21-F21 -> 0 | H21: =$B$3-D21 -> 21 | I21: =IF(ROUND(G21,2)=0,"Paid in Full",IF(H21<=30,"Current (0-30 days)",IF(H21<=60,"31-60 days",IF(H21<=90,"61-90 days","90+ days")))) -> Paid in Full
A22: 6 | B22: SMI-2601-006 | C22: =INDEX('Customer Invoice Index'!$C$2:$C$26,MATCH(B22,'Customer Invoice Index'!$B$2:$B$26,0)) -> Dulles Cloud Campus LLC | D22: =INDEX('Customer Invoice Index'!$E$2:$E$26,MATCH(B22,'Customer Invoice Index'!$B$2:$B$26,0)) -> 46034 | E22: =INDEX('Customer Invoice Index'!$K$2:$K$26,MATCH(B22,'Customer Invoice Index'!$B$2:$B$26,0)) -> 25500 | F22: =SUMIFS('Payment Remittance Batch'!$O$2:$O$21,'Payment Remittance Batch'!$E$2:$E$21,B22)+SUMIFS('Payment Remittance Batch'!$M$2:$M$21,'Payment Remittance Batch'!$E$2:$E$21,B22) -> 0 | G22: =E22-F22 -> 25500 | H22: =$B$3-D22 -> 19 | I22: =IF(ROUND(G22,2)=0,"Paid in Full",IF(H22<=30,"Current (0-30 days)",IF(H22<=60,"31-60 days",IF(H22<=90,"61-90 days","90+ days")))) -> Current (0-30 days)
A23: 7 | B23: SMI-2601-007 | C23: =INDEX('Customer Invoice Index'!$C$2:$C$26,MATCH(B23,'Customer Invoice Index'!$B$2:$B$26,0)) -> Coastal Electric & Controls | D23: =INDEX('Customer Invoice Index'!$E$2:$E$26,MATCH(B23,'Customer Invoice Index'!$B$2:$B$26,0)) -> 46039 | E23: =INDEX('Customer Invoice Index'!$K$2:$K$26,MATCH(B23,'Customer Invoice Index'!$B$2:$B$26,0)) -> 9687.6 | F23: =SUMIFS('Payment Remittance Batch'!$O$2:$O$21,'Payment Remittance Batch'!$E$2:$E$21,B23)+SUMIFS('Payment Remittance Batch'!$M$2:$M$21,'Payment Remittance Batch'!$E$2:$E$21,B23) -> 9503.6 | G23: =E23-F23 -> 184 | H23: =$B$3-D23 -> 14 | I23: =IF(ROUND(G23,2)=0,"Paid in Full",IF(H23<=30,"Current (0-30 days)",IF(H23<=60,"31-60 days",IF(H23<=90,"61-90 days","90+ days")))) -> Current (0-30 days)
A24: 8 | B24: SMI-2601-008 | C24: =INDEX('Customer Invoice Index'!$C$2:$C$26,MATCH(B24,'Customer Invoice Index'!$B$2:$B$26,0)) -> Cavalier Controls Inc. | D24: =INDEX('Customer Invoice Index'!$E$2:$E$26,MATCH(B24,'Customer Invoice Index'!$B$2:$B$26,0)) -> 46040 | E24: =INDEX('Customer Invoice Index'!$K$2:$K$26,MATCH(B24,'Customer Invoice Index'!$B$2:$B$26,0)) -> 14478.75 | F24: =SUMIFS('Payment Remittance Batch'!$O$2:$O$21,'Payment Remittance Batch'!$E$2:$E$21,B24)+SUMIFS('Payment Remittance Batch'!$M$2:$M$21,'Payment Remittance Batch'!$E$2:$E$21,B24) -> 14478.75 | G24: =E24-F24 -> 0 | H24: =$B$3-D24 -> 13 | I24: =IF(ROUND(G24,2)=0,"Paid in Full",IF(H24<=30,"Current (0-30 days)",IF(H24<=60,"31-60 days",IF(H24<=90,"61-90 days","90+ days")))) -> Paid in Full
A25: 9 | B25: SMI-2601-009 | C25: =INDEX('Customer Invoice Index'!$C$2:$C$26,MATCH(B25,'Customer Invoice Index'!$B$2:$B$26,0)) -> Shenandoah Energy Services | D25: =INDEX('Customer Invoice Index'!$E$2:$E$26,MATCH(B25,'Customer Invoice Index'!$B$2:$B$26,0)) -> 46042 | E25: =INDEX('Customer Invoice Index'!$K$2:$K$26,MATCH(B25,'Customer Invoice Index'!$B$2:$B$26,0)) -> 16100 | F25: =SUMIFS('Payment Remittance Batch'!$O$2:$O$21,'Payment Remittance Batch'!$E$2:$E$21,B25)+SUMIFS('Payment Remittance Batch'!$M$2:$M$21,'Payment Remittance Batch'!$E$2:$E$21,B25) -> 0 | G25: =E25-F25 -> 16100 | H25: =$B$3-D25 -> 11 | I25: =IF(ROUND(G25,2)=0,"Paid in Full",IF(H25<=30,"Current (0-30 days)",IF(H25<=60,"31-60 days",IF(H25<=90,"61-90 days","90+ days")))) -> Current (0-30 days)
A26: 10 | B26: SMI-2601-010 | C26: =INDEX('Customer Invoice Index'!$C$2:$C$26,MATCH(B26,'Customer Invoice Index'!$B$2:$B$26,0)) -> Patriot Network Solutions | D26: =INDEX('Customer Invoice Index'!$E$2:$E$26,MATCH(B26,'Customer Invoice Index'!$B$2:$B$26,0)) -> 46044 | E26: =INDEX('Customer Invoice Index'!$K$2:$K$26,MATCH(B26,'Customer Invoice Index'!$B$2:$B$26,0)) -> 9055.8 | F26: =SUMIFS('Payment Remittance Batch'!$O$2:$O$21,'Payment Remittance Batch'!$E$2:$E$21,B26)+SUMIFS('Payment Remittance Batch'!$M$2:$M$21,'Payment Remittance Batch'!$E$2:$E$21,B26) -> 9000 | G26: =E26-F26 -> 55.8 | H26: =$B$3-D26 -> 9 | I26: =IF(ROUND(G26,2)=0,"Paid in Full",IF(H26<=30,"Current (0-30 days)",IF(H26<=60,"31-60 days",IF(H26<=90,"61-90 days","90+ days")))) -> Current (0-30 days)
A27: 11 | B27: SMI-2601-011 | C27: =INDEX('Customer Invoice Index'!$C$2:$C$26,MATCH(B27,'Customer Invoice Index'!$B$2:$B$26,0)) -> Chesapeake Municipal Works | D27: =INDEX('Customer Invoice Index'!$E$2:$E$26,MATCH(B27,'Customer Invoice Index'!$B$2:$B$26,0)) -> 46047 | E27: =INDEX('Customer Invoice Index'!$K$2:$K$26,MATCH(B27,'Customer Invoice Index'!$B$2:$B$26,0)) -> 10250 | F27: =SUMIFS('Payment Remittance Batch'!$O$2:$O$21,'Payment Remittance Batch'!$E$2:$E$21,B27)+SUMIFS('Payment Remittance Batch'!$M$2:$M$21,'Payment Remittance Batch'!$E$2:$E$21,B27) -> 0 | G27: =E27-F27 -> 10250 | H27: =$B$3-D27 -> 6 | I27: =IF(ROUND(G27,2)=0,"Paid in Full",IF(H27<=30,"Current (0-30 days)",IF(H27<=60,"31-60 days",IF(H27<=90,"61-90 days","90+ days")))) -> Current (0-30 days)
A28: 12 | B28: SMI-2601-012 | C28: =INDEX('Customer Invoice Index'!$C$2:$C$26,MATCH(B28,'Customer Invoice Index'!$B$2:$B$26,0)) -> Manassas Telecom Services | D28: =INDEX('Customer Invoice Index'!$E$2:$E$26,MATCH(B28,'Customer Invoice Index'!$B$2:$B$26,0)) -> 46049 | E28: =INDEX('Customer Invoice Index'!$K$2:$K$26,MATCH(B28,'Customer Invoice Index'!$B$2:$B$26,0)) -> 7139.34 | F28: =SUMIFS('Payment Remittance Batch'!$O$2:$O$21,'Payment Remittance Batch'!$E$2:$E$21,B28)+SUMIFS('Payment Remittance Batch'!$M$2:$M$21,'Payment Remittance Batch'!$E$2:$E$21,B28) -> 7139.34 | G28: =E28-F28 -> 0 | H28: =$B$3-D28 -> 4 | I28: =IF(ROUND(G28,2)=0,"Paid in Full",IF(H28<=30,"Current (0-30 days)",IF(H28<=60,"31-60 days",IF(H28<=90,"61-90 days","90+ days")))) -> Paid in Full
... A41: 25 | B41: SMI-2601-025 | C41: =INDEX('Customer Invoice Index'!$C$2:$C$26,MATCH(B41,'Customer Invoice Index'!$B$2:$B$26,0)) -> NOVA FiberBuild Contractors | D41: =INDEX('Customer Invoice Index'!$E$2:$E$26,MATCH(B41,'Customer Invoice Index'!$B$2:$B$26,0)) -> 46052 | E41: =INDEX('Customer Invoice Index'!$K$2:$K$26,MATCH(B41,'Customer Invoice Index'!$B$2:$B$26,0)) -> 12530.7 | F41: =SUMIFS('Payment Remittance Batch'!$O$2:$O$21,'Payment Remittance Batch'!$E$2:$E$21,B41)+SUMIFS('Payment Remittance Batch'!$M$2:$M$21,'Payment Remittance Batch'!$E$2:$E$21,B41) -> 0 | G41: =E41-F41 -> 12530.7 | H41: =$B$3-D41 -> 1 | I41: =IF(ROUND(G41,2)=0,"Paid in Full",IF(H41<=30,"Current (0-30 days)",IF(H41<=60,"31-60 days",IF(H41<=90,"61-90 days","90+ days")))) -> Current (0-30 days)
