Workbook

Sheet Instructions
A1: Month-End Close Checklist
A2: Template for tracking monthly accounting close tasks, ownership, due dates, and status.
A4: Section | B4: Details
A5: Purpose | B5: Template for tracking monthly accounting close tasks, ownership, due dates, and status.
A6: How to Use | B6: 1. Update the Close Month End Date on the Settings sheet. 2. Assign each task owner in the Close_Checklist sheet. 3. Update Status as work progresses. 4. Use Days Late and the Status Summary to identify blockers. 5. Use the Notes column to document issues, reviewer comments, and completion evidence.
A7: Expected Output | B7: • Close task list with owners and deadlines • Open, complete, blocked, and overdue task summary • Evidence notes for review and audit support
A8: Student Rule | B8: Use the sample data first. Then replace the sample rows with your assigned company data. Do not overwrite formula cells unless your instructor tells you to.
A9: Skarion Simulation | B9: These templates support the Skarion Manufacturing LLC accounting job simulation and can be used as student handouts.

Sheet Settings
A1: Settings
A2: Update these inputs before using the checklist.
A4: Input | B4: Value | C4: Notes
A5: Close Month End Date | B5: 46112 | C5: Last day of the month being closed
A6: Close Start Date | B6: =B5+1 -> 46113 | C6: Usually the first day after month-end
A7: Prepared By | B7: Student | C7: Name of preparer
A8: Checklist Review Date | B8: 46114 | C8: Used to calculate Days Late. Update this for practice.

Sheet Close_Checklist
A1: Month-End Close Checklist
A2: Update status and notes as close work is completed.
A4: Step # | B4: Close Day | C4: Area | D4: Task | E4: Owner | F4: Due Date | G4: Status | H4: Days Late | I4: Reviewed By | J4: Notes / Evidence
A5: 1 | B5: 1 | C5: Banking | D5: Import bank activity and confirm beginning balances | E5: Staff Accountant | F5: =Settings!$B$6+B5-1 -> 46113 | G5: Not Started | H5: =IF(G5="Complete",0,MAX(0,Settings!$B$8-F5)) -> 1
A6: 2 | B6: 1 | C6: Banking | D6: Reconcile operating bank account | E6: Staff Accountant | F6: =Settings!$B$6+B6-1 -> 46113 | G6: Not Started | H6: =IF(G6="Complete",0,MAX(0,Settings!$B$8-F6)) -> 1
A7: 3 | B7: 1 | C7: Banking | D7: Reconcile credit card account | E7: Staff Accountant | F7: =Settings!$B$6+B7-1 -> 46113 | G7: Not Started | H7: =IF(G7="Complete",0,MAX(0,Settings!$B$8-F7)) -> 1
A8: 4 | B8: 1 | C8: AR | D8: Post all customer invoices for the month | E8: AR Specialist | F8: =Settings!$B$6+B8-1 -> 46113 | G8: Not Started | H8: =IF(G8="Complete",0,MAX(0,Settings!$B$8-F8)) -> 1
A9: 5 | B9: 1 | C9: AR | D9: Apply customer payments to invoices | E9: AR Specialist | F9: =Settings!$B$6+B9-1 -> 46113 | G9: Not Started | H9: =IF(G9="Complete",0,MAX(0,Settings!$B$8-F9)) -> 1
A10: 6 | B10: 2 | C10: AR | D10: Prepare AR aging and identify overdue accounts | E10: AR Specialist | F10: =Settings!$B$6+B10-1 -> 46114 | G10: Not Started | H10: =IF(G10="Complete",0,MAX(0,Settings!$B$8-F10)) -> 0
A11: 7 | B11: 2 | C11: AP | D11: Enter all vendor bills received by cutoff | E11: AP Specialist | F11: =Settings!$B$6+B11-1 -> 46114 | G11: Not Started | H11: =IF(G11="Complete",0,MAX(0,Settings!$B$8-F11)) -> 0
A12: 8 | B12: 2 | C12: AP | D12: Match vendor bills to purchase orders and receiving records | E12: AP Specialist | F12: =Settings!$B$6+B12-1 -> 46114 | G12: Not Started | H12: =IF(G12="Complete",0,MAX(0,Settings!$B$8-F12)) -> 0
A13: 9 | B13: 2 | C13: AP | D13: Prepare AP aging and payment priority list | E13: AP Specialist | F13: =Settings!$B$6+B13-1 -> 46114 | G13: Not Started | H13: =IF(G13="Complete",0,MAX(0,Settings!$B$8-F13)) -> 0
A14: 10 | B14: 2 | C14: Inventory | D14: Review inventory receiving and usage records | E14: Staff Accountant | F14: =Settings!$B$6+B14-1 -> 46114 | G14: Not Started | H14: =IF(G14="Complete",0,MAX(0,Settings!$B$8-F14)) -> 0
A15: 11 | B15: 3 | C15: Inventory | D15: Post inventory adjustment if physical count differs | E15: Staff Accountant | F15: =Settings!$B$6+B15-1 -> 46115 | G15: Not Started | H15: =IF(G15="Complete",0,MAX(0,Settings!$B$8-F15)) -> 0
A16: 12 | B16: 3 | C16: Payroll | D16: Record payroll journal entry | E16: Payroll Coordinator | F16: =Settings!$B$6+B16-1 -> 46115 | G16: Not Started | H16: =IF(G16="Complete",0,MAX(0,Settings!$B$8-F16)) -> 0
... A34: 30 | B34: 5 | C34: Archive | D34: Save support files and close checklist evidence | E34: Staff Accountant | F34: =Settings!$B$6+B34-1 -> 46117 | G34: Not Started | H34: =IF(G34="Complete",0,MAX(0,Settings!$B$8-F34)) -> 0

Sheet Status_Summary
A1: Close Status Summary
A2: Live summary from the Close_Checklist sheet.
A4: Metric | B4: Count | D4: Area | E4: Total Tasks | F4: Complete | G4: Blocked
A5: Total Tasks | B5: =COUNTA(Close_Checklist!A5:A34) -> 30 | D5: Banking | E5: =COUNTIF(Close_Checklist!$C$5:$C$34,D5) -> 3 | F5: =COUNTIFS(Close_Checklist!$C$5:$C$34,D5,Close_Checklist!$G$5:$G$34,"Complete") -> 0 | G5: =COUNTIFS(Close_Checklist!$C$5:$C$34,D5,Close_Checklist!$G$5:$G$34,"Blocked") -> 0
A6: Complete | B6: =COUNTIF(Close_Checklist!G5:G34,"Complete") -> 0 | D6: AR | E6: =COUNTIF(Close_Checklist!$C$5:$C$34,D6) -> 3 | F6: =COUNTIFS(Close_Checklist!$C$5:$C$34,D6,Close_Checklist!$G$5:$G$34,"Complete") -> 0 | G6: =COUNTIFS(Close_Checklist!$C$5:$C$34,D6,Close_Checklist!$G$5:$G$34,"Blocked") -> 0
A7: In Progress | B7: =COUNTIF(Close_Checklist!G5:G34,"In Progress") -> 0 | D7: AP | E7: =COUNTIF(Close_Checklist!$C$5:$C$34,D7) -> 3 | F7: =COUNTIFS(Close_Checklist!$C$5:$C$34,D7,Close_Checklist!$G$5:$G$34,"Complete") -> 0 | G7: =COUNTIFS(Close_Checklist!$C$5:$C$34,D7,Close_Checklist!$G$5:$G$34,"Blocked") -> 0
A8: Not Started | B8: =COUNTIF(Close_Checklist!G5:G34,"Not Started") -> 30 | D8: Inventory | E8: =COUNTIF(Close_Checklist!$C$5:$C$34,D8) -> 2 | F8: =COUNTIFS(Close_Checklist!$C$5:$C$34,D8,Close_Checklist!$G$5:$G$34,"Complete") -> 0 | G8: =COUNTIFS(Close_Checklist!$C$5:$C$34,D8,Close_Checklist!$G$5:$G$34,"Blocked") -> 0
A9: Blocked | B9: =COUNTIF(Close_Checklist!G5:G34,"Blocked") -> 0 | D9: Payroll | E9: =COUNTIF(Close_Checklist!$C$5:$C$34,D9) -> 3 | F9: =COUNTIFS(Close_Checklist!$C$5:$C$34,D9,Close_Checklist!$G$5:$G$34,"Complete") -> 0 | G9: =COUNTIFS(Close_Checklist!$C$5:$C$34,D9,Close_Checklist!$G$5:$G$34,"Blocked") -> 0
A10: Overdue Open Tasks | B10: =COUNTIFS(Close_Checklist!G5:G34,"<>Complete",Close_Checklist!H5:H34,">0") -> 5 | D10: Fixed Assets | E10: =COUNTIF(Close_Checklist!$C$5:$C$34,D10) -> 2 | F10: =COUNTIFS(Close_Checklist!$C$5:$C$34,D10,Close_Checklist!$G$5:$G$34,"Complete") -> 0 | G10: =COUNTIFS(Close_Checklist!$C$5:$C$34,D10,Close_Checklist!$G$5:$G$34,"Blocked") -> 0
D11: Accruals | E11: =COUNTIF(Close_Checklist!$C$5:$C$34,D11) -> 1 | F11: =COUNTIFS(Close_Checklist!$C$5:$C$34,D11,Close_Checklist!$G$5:$G$34,"Complete") -> 0 | G11: =COUNTIFS(Close_Checklist!$C$5:$C$34,D11,Close_Checklist!$G$5:$G$34,"Blocked") -> 0
D12: Prepaids | E12: =COUNTIF(Close_Checklist!$C$5:$C$34,D12) -> 1 | F12: =COUNTIFS(Close_Checklist!$C$5:$C$34,D12,Close_Checklist!$G$5:$G$34,"Complete") -> 0 | G12: =COUNTIFS(Close_Checklist!$C$5:$C$34,D12,Close_Checklist!$G$5:$G$34,"Blocked") -> 0
D13: Debt | E13: =COUNTIF(Close_Checklist!$C$5:$C$34,D13) -> 1 | F13: =COUNTIFS(Close_Checklist!$C$5:$C$34,D13,Close_Checklist!$G$5:$G$34,"Complete") -> 0 | G13: =COUNTIFS(Close_Checklist!$C$5:$C$34,D13,Close_Checklist!$G$5:$G$34,"Blocked") -> 0
D14: Taxes | E14: =COUNTIF(Close_Checklist!$C$5:$C$34,D14) -> 1 | F14: =COUNTIFS(Close_Checklist!$C$5:$C$34,D14,Close_Checklist!$G$5:$G$34,"Complete") -> 0 | G14: =COUNTIFS(Close_Checklist!$C$5:$C$34,D14,Close_Checklist!$G$5:$G$34,"Blocked") -> 0
D15: GL Review | E15: =COUNTIF(Close_Checklist!$C$5:$C$34,D15) -> 1 | F15: =COUNTIFS(Close_Checklist!$C$5:$C$34,D15,Close_Checklist!$G$5:$G$34,"Complete") -> 0 | G15: =COUNTIFS(Close_Checklist!$C$5:$C$34,D15,Close_Checklist!$G$5:$G$34,"Blocked") -> 0
D16: Reconciliation | E16: =COUNTIF(Close_Checklist!$C$5:$C$34,D16) -> 3 | F16: =COUNTIFS(Close_Checklist!$C$5:$C$34,D16,Close_Checklist!$G$5:$G$34,"Complete") -> 0 | G16: =COUNTIFS(Close_Checklist!$C$5:$C$34,D16,Close_Checklist!$G$5:$G$34,"Blocked") -> 0
D17: Reporting | E17: =COUNTIF(Close_Checklist!$C$5:$C$34,D17) -> 4 | F17: =COUNTIFS(Close_Checklist!$C$5:$C$34,D17,Close_Checklist!$G$5:$G$34,"Complete") -> 0 | G17: =COUNTIFS(Close_Checklist!$C$5:$C$34,D17,Close_Checklist!$G$5:$G$34,"Blocked") -> 0
D18: Review | E18: =COUNTIF(Close_Checklist!$C$5:$C$34,D18) -> 1 | F18: =COUNTIFS(Close_Checklist!$C$5:$C$34,D18,Close_Checklist!$G$5:$G$34,"Complete") -> 0 | G18: =COUNTIFS(Close_Checklist!$C$5:$C$34,D18,Close_Checklist!$G$5:$G$34,"Blocked") -> 0
D19: Archive | E19: =COUNTIF(Close_Checklist!$C$5:$C$34,D19) -> 1 | F19: =COUNTIFS(Close_Checklist!$C$5:$C$34,D19,Close_Checklist!$G$5:$G$34,"Complete") -> 0 | G19: =COUNTIFS(Close_Checklist!$C$5:$C$34,D19,Close_Checklist!$G$5:$G$34,"Blocked") -> 0
