Workbook

Sheet Instructions
A1: AP Aging Report Template
A2: Template for calculating vendor payables and aging buckets by bill.
A4: Section | B4: Details
A5: Purpose | B5: Template for calculating vendor payables and aging buckets by bill.
A6: How to Use | B6: 1. Update the As Of Date on the AP_Aging_Report sheet. 2. Enter vendor bills into Vendor_Bills. 3. Enter payments made against each bill. 4. Review open balances and aging buckets. 5. Use the Vendor Summary to plan which bills should be paid first.
A7: Expected Output | B7: • Current, 1-30, 31-60, 61-90, and 90+ payable balances • Open payable balance by vendor • Payment priority for due and overdue bills
A8: Student Rule | B8: Use the sample data first. Then replace the sample rows with your assigned company data. Do not overwrite formula cells unless your instructor tells you to.
A9: Skarion Simulation | B9: These templates support the Skarion Manufacturing LLC accounting job simulation and can be used as student handouts.

Sheet Vendor_Bills
A1: Vendor Bill Detail
A2: Use this as the AP subledger input sheet.
A4: Vendor | B4: Bill # | C4: Bill Date | D4: Terms Days | E4: Due Date | F4: Original Amount | G4: Payments Made | H4: Open Balance | I4: Days Past Due | J4: Aging Bucket | K4: AP Notes
A5: Dominion Materials LLC | B5: BILL-4101 | C5: 46027 | D5: 30 | E5: =C5+D5 -> 46057 | F5: 8425.5 | G5: 8425.5 | H5: =MAX(0,F5-G5) -> 0 | I5: =IF(H5=0,0,MAX(0,AP_Aging_Report!$B$4-E5)) -> 0 | J5: =IF(H5=0,"Paid",IF(I5=0,"Current",IF(I5<=30,"1-30",IF(I5<=60,"31-60",IF(I5<=90,"61-90","90+"))))) -> Paid
A6: Atlantic Steel Supply | B6: BILL-4102 | C6: 46034 | D6: 30 | E6: =C6+D6 -> 46064 | F6: 12800 | G6: 6000 | H6: =MAX(0,F6-G6) -> 6800 | I6: =IF(H6=0,0,MAX(0,AP_Aging_Report!$B$4-E6)) -> 48 | J6: =IF(H6=0,"Paid",IF(I6=0,"Current",IF(I6<=30,"1-30",IF(I6<=60,"31-60",IF(I6<=90,"61-90","90+"))))) -> 31-60
A7: Piedmont Packaging Co. | B7: BILL-4103 | C7: 46040 | D7: 15 | E7: =C7+D7 -> 46055 | F7: 2190 | G7: 2190 | H7: =MAX(0,F7-G7) -> 0 | I7: =IF(H7=0,0,MAX(0,AP_Aging_Report!$B$4-E7)) -> 0 | J7: =IF(H7=0,"Paid",IF(I7=0,"Current",IF(I7<=30,"1-30",IF(I7<=60,"31-60",IF(I7<=90,"61-90","90+"))))) -> Paid
A8: Ridgeway Freight Services | B8: BILL-4104 | C8: 46044 | D8: 30 | E8: =C8+D8 -> 46074 | F8: 1885.25 | G8: 0 | H8: =MAX(0,F8-G8) -> 1885.25 | I8: =IF(H8=0,0,MAX(0,AP_Aging_Report!$B$4-E8)) -> 38 | J8: =IF(H8=0,"Paid",IF(I8=0,"Current",IF(I8<=30,"1-30",IF(I8<=60,"31-60",IF(I8<=90,"61-90","90+"))))) -> 31-60
A9: BlueLine Labels | B9: BILL-4105 | C9: 46049 | D9: 30 | E9: =C9+D9 -> 46079 | F9: 990 | G9: 0 | H9: =MAX(0,F9-G9) -> 990 | I9: =IF(H9=0,0,MAX(0,AP_Aging_Report!$B$4-E9)) -> 33 | J9: =IF(H9=0,"Paid",IF(I9=0,"Current",IF(I9<=30,"1-30",IF(I9<=60,"31-60",IF(I9<=90,"61-90","90+"))))) -> 31-60
A10: National Resin Co. | B10: BILL-4106 | C10: 46054 | D10: 30 | E10: =C10+D10 -> 46084 | F10: 6225 | G10: 0 | H10: =MAX(0,F10-G10) -> 6225 | I10: =IF(H10=0,0,MAX(0,AP_Aging_Report!$B$4-E10)) -> 28 | J10: =IF(H10=0,"Paid",IF(I10=0,"Current",IF(I10<=30,"1-30",IF(I10<=60,"31-60",IF(I10<=90,"61-90","90+"))))) -> 1-30
A11: SafetyFirst Supplies | B11: BILL-4107 | C11: 46056 | D11: 15 | E11: =C11+D11 -> 46071 | F11: 1250 | G11: 0 | H11: =MAX(0,F11-G11) -> 1250 | I11: =IF(H11=0,0,MAX(0,AP_Aging_Report!$B$4-E11)) -> 41 | J11: =IF(H11=0,"Paid",IF(I11=0,"Current",IF(I11<=30,"1-30",IF(I11<=60,"31-60",IF(I11<=90,"61-90","90+"))))) -> 31-60
A12: Capital Machinery Leasing | B12: BILL-4108 | C12: 46059 | D12: 30 | E12: =C12+D12 -> 46089 | F12: 4160 | G12: 4160 | H12: =MAX(0,F12-G12) -> 0 | I12: =IF(H12=0,0,MAX(0,AP_Aging_Report!$B$4-E12)) -> 0 | J12: =IF(H12=0,"Paid",IF(I12=0,"Current",IF(I12<=30,"1-30",IF(I12<=60,"31-60",IF(I12<=90,"61-90","90+"))))) -> Paid
A13: Virginia Office Supply | B13: BILL-4109 | C13: 46062 | D13: 30 | E13: =C13+D13 -> 46092 | F13: 745.9 | G13: 0 | H13: =MAX(0,F13-G13) -> 745.9 | I13: =IF(H13=0,0,MAX(0,AP_Aging_Report!$B$4-E13)) -> 20 | J13: =IF(H13=0,"Paid",IF(I13=0,"Current",IF(I13<=30,"1-30",IF(I13<=60,"31-60",IF(I13<=90,"61-90","90+"))))) -> 1-30
A14: Skyline Janitorial | B14: BILL-4110 | C14: 46064 | D14: 15 | E14: =C14+D14 -> 46079 | F14: 685 | G14: 0 | H14: =MAX(0,F14-G14) -> 685 | I14: =IF(H14=0,0,MAX(0,AP_Aging_Report!$B$4-E14)) -> 33 | J14: =IF(H14=0,"Paid",IF(I14=0,"Current",IF(I14<=30,"1-30",IF(I14<=60,"31-60",IF(I14<=90,"61-90","90+"))))) -> 31-60
A15: Fairfax Industrial Park | B15: BILL-4111 | C15: 46068 | D15: 0 | E15: =C15+D15 -> 46068 | F15: 8750 | G15: 8750 | H15: =MAX(0,F15-G15) -> 0 | I15: =IF(H15=0,0,MAX(0,AP_Aging_Report!$B$4-E15)) -> 0 | J15: =IF(H15=0,"Paid",IF(I15=0,"Current",IF(I15<=30,"1-30",IF(I15<=60,"31-60",IF(I15<=90,"61-90","90+"))))) -> Paid
A16: Dominion Energy | B16: BILL-4112 | C16: 46072 | D16: 15 | E16: =C16+D16 -> 46087 | F16: 1280.75 | G16: 0 | H16: =MAX(0,F16-G16) -> 1280.75 | I16: =IF(H16=0,0,MAX(0,AP_Aging_Report!$B$4-E16)) -> 25 | J16: =IF(H16=0,"Paid",IF(I16=0,"Current",IF(I16<=30,"1-30",IF(I16<=60,"31-60",IF(I16<=90,"61-90","90+"))))) -> 1-30
... A32: DataSafe Cloud Backup | B32: BILL-4128 | C32: 46111 | D32: 0 | E32: =C32+D32 -> 46111 | F32: 425 | G32: 425 | H32: =MAX(0,F32-G32) -> 0 | I32: =IF(H32=0,0,MAX(0,AP_Aging_Report!$B$4-E32)) -> 0 | J32: =IF(H32=0,"Paid",IF(I32=0,"Current",IF(I32<=30,"1-30",IF(I32<=60,"31-60",IF(I32<=90,"61-90","90+"))))) -> Paid

Sheet AP_Aging_Report
A1: AP Aging Report
A2: Open vendor payables by aging bucket.
A4: As Of Date | B4: 46112
A5: Prepared By | B5: Student
A8: Aging Bucket | B8: Amount | D8: Vendor | E8: Current | F8: 1-30 | G8: 31-60 | H8: 61-90 | I8: 90+ | J8: Total
A9: Current | B9: =SUMIFS(Vendor_Bills!$H$5:$H$32,Vendor_Bills!$J$5:$J$32,A9) -> 40465 | D9: Atlantic Steel Supply | E9: =SUMIFS(Vendor_Bills!$H$5:$H$32,Vendor_Bills!$A$5:$A$32,$D9,Vendor_Bills!$J$5:$J$32,E$8) -> 11800 | F9: =SUMIFS(Vendor_Bills!$H$5:$H$32,Vendor_Bills!$A$5:$A$32,$D9,Vendor_Bills!$J$5:$J$32,F$8) -> 0 | G9: =SUMIFS(Vendor_Bills!$H$5:$H$32,Vendor_Bills!$A$5:$A$32,$D9,Vendor_Bills!$J$5:$J$32,G$8) -> 6800 | H9: =SUMIFS(Vendor_Bills!$H$5:$H$32,Vendor_Bills!$A$5:$A$32,$D9,Vendor_Bills!$J$5:$J$32,H$8) -> 0 | I9: =SUMIFS(Vendor_Bills!$H$5:$H$32,Vendor_Bills!$A$5:$A$32,$D9,Vendor_Bills!$J$5:$J$32,I$8) -> 0 | J9: =SUM(E9:I9) -> 18600
A10: 1-30 | B10: =SUMIFS(Vendor_Bills!$H$5:$H$32,Vendor_Bills!$J$5:$J$32,A10) -> 14126.65 | D10: Blue Ridge Maintenance | E10: =SUMIFS(Vendor_Bills!$H$5:$H$32,Vendor_Bills!$A$5:$A$32,$D10,Vendor_Bills!$J$5:$J$32,E$8) -> 2780 | F10: =SUMIFS(Vendor_Bills!$H$5:$H$32,Vendor_Bills!$A$5:$A$32,$D10,Vendor_Bills!$J$5:$J$32,F$8) -> 0 | G10: =SUMIFS(Vendor_Bills!$H$5:$H$32,Vendor_Bills!$A$5:$A$32,$D10,Vendor_Bills!$J$5:$J$32,G$8) -> 0 | H10: =SUMIFS(Vendor_Bills!$H$5:$H$32,Vendor_Bills!$A$5:$A$32,$D10,Vendor_Bills!$J$5:$J$32,H$8) -> 0 | I10: =SUMIFS(Vendor_Bills!$H$5:$H$32,Vendor_Bills!$A$5:$A$32,$D10,Vendor_Bills!$J$5:$J$32,I$8) -> 0 | J10: =SUM(E10:I10) -> 2780
A11: 31-60 | B11: =SUMIFS(Vendor_Bills!$H$5:$H$32,Vendor_Bills!$J$5:$J$32,A11) -> 11610.25 | D11: BlueLine Labels | E11: =SUMIFS(Vendor_Bills!$H$5:$H$32,Vendor_Bills!$A$5:$A$32,$D11,Vendor_Bills!$J$5:$J$32,E$8) -> 1240 | F11: =SUMIFS(Vendor_Bills!$H$5:$H$32,Vendor_Bills!$A$5:$A$32,$D11,Vendor_Bills!$J$5:$J$32,F$8) -> 0 | G11: =SUMIFS(Vendor_Bills!$H$5:$H$32,Vendor_Bills!$A$5:$A$32,$D11,Vendor_Bills!$J$5:$J$32,G$8) -> 990 | H11: =SUMIFS(Vendor_Bills!$H$5:$H$32,Vendor_Bills!$A$5:$A$32,$D11,Vendor_Bills!$J$5:$J$32,H$8) -> 0 | I11: =SUMIFS(Vendor_Bills!$H$5:$H$32,Vendor_Bills!$A$5:$A$32,$D11,Vendor_Bills!$J$5:$J$32,I$8) -> 0 | J11: =SUM(E11:I11) -> 2230
A12: 61-90 | B12: =SUMIFS(Vendor_Bills!$H$5:$H$32,Vendor_Bills!$J$5:$J$32,A12) -> 0 | D12: Capital Machinery Leasing | E12: =SUMIFS(Vendor_Bills!$H$5:$H$32,Vendor_Bills!$A$5:$A$32,$D12,Vendor_Bills!$J$5:$J$32,E$8) -> 0 | F12: =SUMIFS(Vendor_Bills!$H$5:$H$32,Vendor_Bills!$A$5:$A$32,$D12,Vendor_Bills!$J$5:$J$32,F$8) -> 0 | G12: =SUMIFS(Vendor_Bills!$H$5:$H$32,Vendor_Bills!$A$5:$A$32,$D12,Vendor_Bills!$J$5:$J$32,G$8) -> 0 | H12: =SUMIFS(Vendor_Bills!$H$5:$H$32,Vendor_Bills!$A$5:$A$32,$D12,Vendor_Bills!$J$5:$J$32,H$8) -> 0 | I12: =SUMIFS(Vendor_Bills!$H$5:$H$32,Vendor_Bills!$A$5:$A$32,$D12,Vendor_Bills!$J$5:$J$32,I$8) -> 0 | J12: =SUM(E12:I12) -> 0
A13: 90+ | B13: =SUMIFS(Vendor_Bills!$H$5:$H$32,Vendor_Bills!$J$5:$J$32,A13) -> 0 | D13: DataSafe Cloud Backup | E13: =SUMIFS(Vendor_Bills!$H$5:$H$32,Vendor_Bills!$A$5:$A$32,$D13,Vendor_Bills!$J$5:$J$32,E$8) -> 0 | F13: =SUMIFS(Vendor_Bills!$H$5:$H$32,Vendor_Bills!$A$5:$A$32,$D13,Vendor_Bills!$J$5:$J$32,F$8) -> 0 | G13: =SUMIFS(Vendor_Bills!$H$5:$H$32,Vendor_Bills!$A$5:$A$32,$D13,Vendor_Bills!$J$5:$J$32,G$8) -> 0 | H13: =SUMIFS(Vendor_Bills!$H$5:$H$32,Vendor_Bills!$A$5:$A$32,$D13,Vendor_Bills!$J$5:$J$32,H$8) -> 0 | I13: =SUMIFS(Vendor_Bills!$H$5:$H$32,Vendor_Bills!$A$5:$A$32,$D13,Vendor_Bills!$J$5:$J$32,I$8) -> 0 | J13: =SUM(E13:I13) -> 0
A14: Total Open AP | B14: =SUM(B9:B13) -> 66201.9 | D14: Dominion Energy | E14: =SUMIFS(Vendor_Bills!$H$5:$H$32,Vendor_Bills!$A$5:$A$32,$D14,Vendor_Bills!$J$5:$J$32,E$8) -> 1395 | F14: =SUMIFS(Vendor_Bills!$H$5:$H$32,Vendor_Bills!$A$5:$A$32,$D14,Vendor_Bills!$J$5:$J$32,F$8) -> 1280.75 | G14: =SUMIFS(Vendor_Bills!$H$5:$H$32,Vendor_Bills!$A$5:$A$32,$D14,Vendor_Bills!$J$5:$J$32,G$8) -> 0 | H14: =SUMIFS(Vendor_Bills!$H$5:$H$32,Vendor_Bills!$A$5:$A$32,$D14,Vendor_Bills!$J$5:$J$32,H$8) -> 0 | I14: =SUMIFS(Vendor_Bills!$H$5:$H$32,Vendor_Bills!$A$5:$A$32,$D14,Vendor_Bills!$J$5:$J$32,I$8) -> 0 | J14: =SUM(E14:I14) -> 2675.75
D15: Dominion Materials LLC | E15: =SUMIFS(Vendor_Bills!$H$5:$H$32,Vendor_Bills!$A$5:$A$32,$D15,Vendor_Bills!$J$5:$J$32,E$8) -> 9750 | F15: =SUMIFS(Vendor_Bills!$H$5:$H$32,Vendor_Bills!$A$5:$A$32,$D15,Vendor_Bills!$J$5:$J$32,F$8) -> 0 | G15: =SUMIFS(Vendor_Bills!$H$5:$H$32,Vendor_Bills!$A$5:$A$32,$D15,Vendor_Bills!$J$5:$J$32,G$8) -> 0 | H15: =SUMIFS(Vendor_Bills!$H$5:$H$32,Vendor_Bills!$A$5:$A$32,$D15,Vendor_Bills!$J$5:$J$32,H$8) -> 0 | I15: =SUMIFS(Vendor_Bills!$H$5:$H$32,Vendor_Bills!$A$5:$A$32,$D15,Vendor_Bills!$J$5:$J$32,I$8) -> 0 | J15: =SUM(E15:I15) -> 9750
D16: Fairfax Industrial Park | E16: =SUMIFS(Vendor_Bills!$H$5:$H$32,Vendor_Bills!$A$5:$A$32,$D16,Vendor_Bills!$J$5:$J$32,E$8) -> 0 | F16: =SUMIFS(Vendor_Bills!$H$5:$H$32,Vendor_Bills!$A$5:$A$32,$D16,Vendor_Bills!$J$5:$J$32,F$8) -> 0 | G16: =SUMIFS(Vendor_Bills!$H$5:$H$32,Vendor_Bills!$A$5:$A$32,$D16,Vendor_Bills!$J$5:$J$32,G$8) -> 0 | H16: =SUMIFS(Vendor_Bills!$H$5:$H$32,Vendor_Bills!$A$5:$A$32,$D16,Vendor_Bills!$J$5:$J$32,H$8) -> 0 | I16: =SUMIFS(Vendor_Bills!$H$5:$H$32,Vendor_Bills!$A$5:$A$32,$D16,Vendor_Bills!$J$5:$J$32,I$8) -> 0 | J16: =SUM(E16:I16) -> 0
D17: Hampton Roads Insurance | E17: =SUMIFS(Vendor_Bills!$H$5:$H$32,Vendor_Bills!$A$5:$A$32,$D17,Vendor_Bills!$J$5:$J$32,E$8) -> 1950 | F17: =SUMIFS(Vendor_Bills!$H$5:$H$32,Vendor_Bills!$A$5:$A$32,$D17,Vendor_Bills!$J$5:$J$32,F$8) -> 1950 | G17: =SUMIFS(Vendor_Bills!$H$5:$H$32,Vendor_Bills!$A$5:$A$32,$D17,Vendor_Bills!$J$5:$J$32,G$8) -> 0 | H17: =SUMIFS(Vendor_Bills!$H$5:$H$32,Vendor_Bills!$A$5:$A$32,$D17,Vendor_Bills!$J$5:$J$32,H$8) -> 0 | I17: =SUMIFS(Vendor_Bills!$H$5:$H$32,Vendor_Bills!$A$5:$A$32,$D17,Vendor_Bills!$J$5:$J$32,I$8) -> 0 | J17: =SUM(E17:I17) -> 3900
D18: National Resin Co. | E18: =SUMIFS(Vendor_Bills!$H$5:$H$32,Vendor_Bills!$A$5:$A$32,$D18,Vendor_Bills!$J$5:$J$32,E$8) -> 7100 | F18: =SUMIFS(Vendor_Bills!$H$5:$H$32,Vendor_Bills!$A$5:$A$32,$D18,Vendor_Bills!$J$5:$J$32,F$8) -> 6225 | G18: =SUMIFS(Vendor_Bills!$H$5:$H$32,Vendor_Bills!$A$5:$A$32,$D18,Vendor_Bills!$J$5:$J$32,G$8) -> 0 | H18: =SUMIFS(Vendor_Bills!$H$5:$H$32,Vendor_Bills!$A$5:$A$32,$D18,Vendor_Bills!$J$5:$J$32,H$8) -> 0 | I18: =SUMIFS(Vendor_Bills!$H$5:$H$32,Vendor_Bills!$A$5:$A$32,$D18,Vendor_Bills!$J$5:$J$32,I$8) -> 0 | J18: =SUM(E18:I18) -> 13325
D19: Piedmont Packaging Co. | E19: =SUMIFS(Vendor_Bills!$H$5:$H$32,Vendor_Bills!$A$5:$A$32,$D19,Vendor_Bills!$J$5:$J$32,E$8) -> 0 | F19: =SUMIFS(Vendor_Bills!$H$5:$H$32,Vendor_Bills!$A$5:$A$32,$D19,Vendor_Bills!$J$5:$J$32,F$8) -> 2495 | G19: =SUMIFS(Vendor_Bills!$H$5:$H$32,Vendor_Bills!$A$5:$A$32,$D19,Vendor_Bills!$J$5:$J$32,G$8) -> 0 | H19: =SUMIFS(Vendor_Bills!$H$5:$H$32,Vendor_Bills!$A$5:$A$32,$D19,Vendor_Bills!$J$5:$J$32,H$8) -> 0 | I19: =SUMIFS(Vendor_Bills!$H$5:$H$32,Vendor_Bills!$A$5:$A$32,$D19,Vendor_Bills!$J$5:$J$32,I$8) -> 0 | J19: =SUM(E19:I19) -> 2495
D20: QuickBooks Payroll | E20: =SUMIFS(Vendor_Bills!$H$5:$H$32,Vendor_Bills!$A$5:$A$32,$D20,Vendor_Bills!$J$5:$J$32,E$8) -> 0 | F20: =SUMIFS(Vendor_Bills!$H$5:$H$32,Vendor_Bills!$A$5:$A$32,$D20,Vendor_Bills!$J$5:$J$32,F$8) -> 0 | G20: =SUMIFS(Vendor_Bills!$H$5:$H$32,Vendor_Bills!$A$5:$A$32,$D20,Vendor_Bills!$J$5:$J$32,G$8) -> 0 | H20: =SUMIFS(Vendor_Bills!$H$5:$H$32,Vendor_Bills!$A$5:$A$32,$D20,Vendor_Bills!$J$5:$J$32,H$8) -> 0 | I20: =SUMIFS(Vendor_Bills!$H$5:$H$32,Vendor_Bills!$A$5:$A$32,$D20,Vendor_Bills!$J$5:$J$32,I$8) -> 0 | J20: =SUM(E20:I20) -> 0
D21: Richmond Tax Advisors | E21: =SUMIFS(Vendor_Bills!$H$5:$H$32,Vendor_Bills!$A$5:$A$32,$D21,Vendor_Bills!$J$5:$J$32,E$8) -> 2400 | F21: =SUMIFS(Vendor_Bills!$H$5:$H$32,Vendor_Bills!$A$5:$A$32,$D21,Vendor_Bills!$J$5:$J$32,F$8) -> 0 | G21: =SUMIFS(Vendor_Bills!$H$5:$H$32,Vendor_Bills!$A$5:$A$32,$D21,Vendor_Bills!$J$5:$J$32,G$8) -> 0 | H21: =SUMIFS(Vendor_Bills!$H$5:$H$32,Vendor_Bills!$A$5:$A$32,$D21,Vendor_Bills!$J$5:$J$32,H$8) -> 0 | I21: =SUMIFS(Vendor_Bills!$H$5:$H$32,Vendor_Bills!$A$5:$A$32,$D21,Vendor_Bills!$J$5:$J$32,I$8) -> 0 | J21: =SUM(E21:I21) -> 2400
D22: Ridgeway Freight Services | E22: =SUMIFS(Vendor_Bills!$H$5:$H$32,Vendor_Bills!$A$5:$A$32,$D22,Vendor_Bills!$J$5:$J$32,E$8) -> 2050 | F22: =SUMIFS(Vendor_Bills!$H$5:$H$32,Vendor_Bills!$A$5:$A$32,$D22,Vendor_Bills!$J$5:$J$32,F$8) -> 0 | G22: =SUMIFS(Vendor_Bills!$H$5:$H$32,Vendor_Bills!$A$5:$A$32,$D22,Vendor_Bills!$J$5:$J$32,G$8) -> 1885.25 | H22: =SUMIFS(Vendor_Bills!$H$5:$H$32,Vendor_Bills!$A$5:$A$32,$D22,Vendor_Bills!$J$5:$J$32,H$8) -> 0 | I22: =SUMIFS(Vendor_Bills!$H$5:$H$32,Vendor_Bills!$A$5:$A$32,$D22,Vendor_Bills!$J$5:$J$32,I$8) -> 0 | J22: =SUM(E22:I22) -> 3935.25
D23: SafetyFirst Supplies | E23: =SUMIFS(Vendor_Bills!$H$5:$H$32,Vendor_Bills!$A$5:$A$32,$D23,Vendor_Bills!$J$5:$J$32,E$8) -> 0 | F23: =SUMIFS(Vendor_Bills!$H$5:$H$32,Vendor_Bills!$A$5:$A$32,$D23,Vendor_Bills!$J$5:$J$32,F$8) -> 1430 | G23: =SUMIFS(Vendor_Bills!$H$5:$H$32,Vendor_Bills!$A$5:$A$32,$D23,Vendor_Bills!$J$5:$J$32,G$8) -> 1250 | H23: =SUMIFS(Vendor_Bills!$H$5:$H$32,Vendor_Bills!$A$5:$A$32,$D23,Vendor_Bills!$J$5:$J$32,H$8) -> 0 | I23: =SUMIFS(Vendor_Bills!$H$5:$H$32,Vendor_Bills!$A$5:$A$32,$D23,Vendor_Bills!$J$5:$J$32,I$8) -> 0 | J23: =SUM(E23:I23) -> 2680
D24: Skyline Janitorial | E24: =SUMIFS(Vendor_Bills!$H$5:$H$32,Vendor_Bills!$A$5:$A$32,$D24,Vendor_Bills!$J$5:$J$32,E$8) -> 0 | F24: =SUMIFS(Vendor_Bills!$H$5:$H$32,Vendor_Bills!$A$5:$A$32,$D24,Vendor_Bills!$J$5:$J$32,F$8) -> 0 | G24: =SUMIFS(Vendor_Bills!$H$5:$H$32,Vendor_Bills!$A$5:$A$32,$D24,Vendor_Bills!$J$5:$J$32,G$8) -> 685 | H24: =SUMIFS(Vendor_Bills!$H$5:$H$32,Vendor_Bills!$A$5:$A$32,$D24,Vendor_Bills!$J$5:$J$32,H$8) -> 0 | I24: =SUMIFS(Vendor_Bills!$H$5:$H$32,Vendor_Bills!$A$5:$A$32,$D24,Vendor_Bills!$J$5:$J$32,I$8) -> 0 | J24: =SUM(E24:I24) -> 685
D25: Virginia Office Supply | E25: =SUMIFS(Vendor_Bills!$H$5:$H$32,Vendor_Bills!$A$5:$A$32,$D25,Vendor_Bills!$J$5:$J$32,E$8) -> 0 | F25: =SUMIFS(Vendor_Bills!$H$5:$H$32,Vendor_Bills!$A$5:$A$32,$D25,Vendor_Bills!$J$5:$J$32,F$8) -> 745.9 | G25: =SUMIFS(Vendor_Bills!$H$5:$H$32,Vendor_Bills!$A$5:$A$32,$D25,Vendor_Bills!$J$5:$J$32,G$8) -> 0 | H25: =SUMIFS(Vendor_Bills!$H$5:$H$32,Vendor_Bills!$A$5:$A$32,$D25,Vendor_Bills!$J$5:$J$32,H$8) -> 0 | I25: =SUMIFS(Vendor_Bills!$H$5:$H$32,Vendor_Bills!$A$5:$A$32,$D25,Vendor_Bills!$J$5:$J$32,I$8) -> 0 | J25: =SUM(E25:I25) -> 745.9
