Workbook

Sheet Instructions
A1: Bank Reconciliation Worksheet
A2: Template for matching bank statement activity to the cash general ledger and documenting reconciling items.
A4: Section | B4: Details
A5: Purpose | B5: Template for matching bank statement activity to the cash general ledger and documenting reconciling items.
A6: How to Use | B6: 1. Paste or type bank statement transactions into the Bank_Import sheet. 2. Paste or type cash GL transactions into the GL_Import sheet. 3. Use the Status column to identify matched, unmatched, and possible duplicate transactions. 4. Complete the Reconciliation sheet and explain each difference in the Difference_Log. 5. The goal is for Adjusted Bank Balance and Adjusted Book Balance to agree.
A7: Expected Output | B7: • Matched transaction list • Deposits in transit • Outstanding checks/payments • Bank fees or interest missing from books • Final reconciliation difference
A8: Student Rule | B8: Use the sample data first. Then replace the sample rows with your assigned company data. Do not overwrite formula cells unless your instructor tells you to.
A9: Skarion Simulation | B9: These templates support the Skarion Manufacturing LLC accounting job simulation and can be used as student handouts.

Sheet Bank_Import
A1: Bank Import / Statement Transactions
A2: Sample data can be replaced with actual bank statement exports.
A4: Date | B4: Bank Ref | C4: Description | D4: Deposit | E4: Withdrawal | F4: Amount | G4: Match Key | H4: GL Match Count | I4: Status | J4: Student Notes
A5: 46024 | B5: ACH-DEP-1001 | C5: Customer ACH Deposit - Blue Ridge Retail | D5: 4200 | E5: 0 | F5: =D5-E5 | G5: =TEXT(A5,"yyyymmdd")&"|"&TEXT(ROUND(ABS(F5),2),"0.00") | H5: =COUNTIFS(GL_Import!$G$5:$G$45,G5) | I5: =IF(H5=0,"Unmatched",IF(H5>1,"Possible Duplicate","Matched"))
A6: 46025 | B6: CHK-2201 | C6: Cleared Check - Dominion Materials | D6: 0 | E6: 3150 | F6: =D6-E6 | G6: =TEXT(A6,"yyyymmdd")&"|"&TEXT(ROUND(ABS(F6),2),"0.00") | H6: =COUNTIFS(GL_Import!$G$5:$G$45,G6) | I6: =IF(H6=0,"Unmatched",IF(H6>1,"Possible Duplicate","Matched"))
A7: 46026 | B7: ACH-UTIL | C7: ACH Debit - Dominion Energy | D7: 0 | E7: 1280.75 | F7: =D7-E7 | G7: =TEXT(A7,"yyyymmdd")&"|"&TEXT(ROUND(ABS(F7),2),"0.00") | H7: =COUNTIFS(GL_Import!$G$5:$G$45,G7) | I7: =IF(H7=0,"Unmatched",IF(H7>1,"Possible Duplicate","Matched"))
A8: 46027 | B8: ACH-DEP-1002 | C8: Customer ACH Deposit - Shenandoah Builders | D8: 5850 | E8: 0 | F8: =D8-E8 | G8: =TEXT(A8,"yyyymmdd")&"|"&TEXT(ROUND(ABS(F8),2),"0.00") | H8: =COUNTIFS(GL_Import!$G$5:$G$45,G8) | I8: =IF(H8=0,"Unmatched",IF(H8>1,"Possible Duplicate","Matched"))
A9: 46028 | B9: WIRE-7001 | C9: Wire Payment - Atlantic Steel | D9: 0 | E9: 8425.5 | F9: =D9-E9 | G9: =TEXT(A9,"yyyymmdd")&"|"&TEXT(ROUND(ABS(F9),2),"0.00") | H9: =COUNTIFS(GL_Import!$G$5:$G$45,G9) | I9: =IF(H9=0,"Unmatched",IF(H9>1,"Possible Duplicate","Matched"))
A10: 46029 | B10: ACH-DEP-1003 | C10: Customer ACH Deposit - Cardinal HVAC | D10: 3725 | E10: 0 | F10: =D10-E10 | G10: =TEXT(A10,"yyyymmdd")&"|"&TEXT(ROUND(ABS(F10),2),"0.00") | H10: =COUNTIFS(GL_Import!$G$5:$G$45,G10) | I10: =IF(H10=0,"Unmatched",IF(H10>1,"Possible Duplicate","Matched"))
A11: 46030 | B11: CHK-2202 | C11: Cleared Check - Piedmont Packaging | D11: 0 | E11: 2190 | F11: =D11-E11 | G11: =TEXT(A11,"yyyymmdd")&"|"&TEXT(ROUND(ABS(F11),2),"0.00") | H11: =COUNTIFS(GL_Import!$G$5:$G$45,G11) | I11: =IF(H11=0,"Unmatched",IF(H11>1,"Possible Duplicate","Matched"))
A12: 46030 | B12: BANK-FEE | C12: Monthly Bank Service Fee | D12: 0 | E12: 35 | F12: =D12-E12 | G12: =TEXT(A12,"yyyymmdd")&"|"&TEXT(ROUND(ABS(F12),2),"0.00") | H12: =COUNTIFS(GL_Import!$G$5:$G$45,G12) | I12: =IF(H12=0,"Unmatched",IF(H12>1,"Possible Duplicate","Matched"))
A13: 46031 | B13: ACH-PAYROLL | C13: Payroll Direct Deposit | D13: 0 | E13: 26500 | F13: =D13-E13 | G13: =TEXT(A13,"yyyymmdd")&"|"&TEXT(ROUND(ABS(F13),2),"0.00") | H13: =COUNTIFS(GL_Import!$G$5:$G$45,G13) | I13: =IF(H13=0,"Unmatched",IF(H13>1,"Possible Duplicate","Matched"))
A14: 46032 | B14: ACH-DEP-1004 | C14: Customer ACH Deposit - Coastal Supply | D14: 6100 | E14: 0 | F14: =D14-E14 | G14: =TEXT(A14,"yyyymmdd")&"|"&TEXT(ROUND(ABS(F14),2),"0.00") | H14: =COUNTIFS(GL_Import!$G$5:$G$45,G14) | I14: =IF(H14=0,"Unmatched",IF(H14>1,"Possible Duplicate","Matched"))
A15: 46033 | B15: CHK-2203 | C15: Cleared Check - Virginia Office Supply | D15: 0 | E15: 745.9 | F15: =D15-E15 | G15: =TEXT(A15,"yyyymmdd")&"|"&TEXT(ROUND(ABS(F15),2),"0.00") | H15: =COUNTIFS(GL_Import!$G$5:$G$45,G15) | I15: =IF(H15=0,"Unmatched",IF(H15>1,"Possible Duplicate","Matched"))
A16: 46034 | B16: ACH-SUB | C16: ACH Debit - QuickBooks Payroll | D16: 0 | E16: 348 | F16: =D16-E16 | G16: =TEXT(A16,"yyyymmdd")&"|"&TEXT(ROUND(ABS(F16),2),"0.00") | H16: =COUNTIFS(GL_Import!$G$5:$G$45,G16) | I16: =IF(H16=0,"Unmatched",IF(H16>1,"Possible Duplicate","Matched"))
... A36: 46053 | B36: ACH-TAX | C36: Payroll Tax Payment | D36: 0 | E36: 7025 | F36: =D36-E36 | G36: =TEXT(A36,"yyyymmdd")&"|"&TEXT(ROUND(ABS(F36),2),"0.00") | H36: =COUNTIFS(GL_Import!$G$5:$G$45,G36) | I36: =IF(H36=0,"Unmatched",IF(H36>1,"Possible Duplicate","Matched"))

Sheet GL_Import
A1: GL Import / Cash Account Transactions
A2: Sample general ledger cash activity for matching against bank activity.
A4: Date | B4: GL Ref | C4: Description | D4: Receipt | E4: Payment | F4: Amount | G4: Match Key | H4: Bank Match Count | I4: Status | J4: Student Notes
A5: 46024 | B5: DEP-1001 | C5: Receipt - Blue Ridge Retail | D5: 4200 | E5: 0 | F5: =D5-E5 | G5: =TEXT(A5,"yyyymmdd")&"|"&TEXT(ROUND(ABS(F5),2),"0.00") | H5: =COUNTIFS(Bank_Import!$G$5:$G$45,G5) | I5: =IF(COUNTIFS($G$5:$G$45,G5)>1,"Possible Duplicate",IF(H5=0,"Unmatched",IF(H5>1,"Possible Duplicate","Matched")))
A6: 46025 | B6: BILLPAY-2201 | C6: Payment - Dominion Materials | D6: 0 | E6: 3150 | F6: =D6-E6 | G6: =TEXT(A6,"yyyymmdd")&"|"&TEXT(ROUND(ABS(F6),2),"0.00") | H6: =COUNTIFS(Bank_Import!$G$5:$G$45,G6) | I6: =IF(COUNTIFS($G$5:$G$45,G6)>1,"Possible Duplicate",IF(H6=0,"Unmatched",IF(H6>1,"Possible Duplicate","Matched")))
A7: 46026 | B7: UTIL-JAN | C7: Utility Payment - Dominion Energy | D7: 0 | E7: 1280.75 | F7: =D7-E7 | G7: =TEXT(A7,"yyyymmdd")&"|"&TEXT(ROUND(ABS(F7),2),"0.00") | H7: =COUNTIFS(Bank_Import!$G$5:$G$45,G7) | I7: =IF(COUNTIFS($G$5:$G$45,G7)>1,"Possible Duplicate",IF(H7=0,"Unmatched",IF(H7>1,"Possible Duplicate","Matched")))
A8: 46027 | B8: DEP-1002 | C8: Receipt - Shenandoah Builders | D8: 5580 | E8: 0 | F8: =D8-E8 | G8: =TEXT(A8,"yyyymmdd")&"|"&TEXT(ROUND(ABS(F8),2),"0.00") | H8: =COUNTIFS(Bank_Import!$G$5:$G$45,G8) | I8: =IF(COUNTIFS($G$5:$G$45,G8)>1,"Possible Duplicate",IF(H8=0,"Unmatched",IF(H8>1,"Possible Duplicate","Matched"))) | J8: Entered wrong amount; bank shows 5,850
A9: 46028 | B9: BILLPAY-7001 | C9: Payment - Atlantic Steel | D9: 0 | E9: 8425.5 | F9: =D9-E9 | G9: =TEXT(A9,"yyyymmdd")&"|"&TEXT(ROUND(ABS(F9),2),"0.00") | H9: =COUNTIFS(Bank_Import!$G$5:$G$45,G9) | I9: =IF(COUNTIFS($G$5:$G$45,G9)>1,"Possible Duplicate",IF(H9=0,"Unmatched",IF(H9>1,"Possible Duplicate","Matched")))
A10: 46029 | B10: DEP-1003 | C10: Receipt - Cardinal HVAC | D10: 3725 | E10: 0 | F10: =D10-E10 | G10: =TEXT(A10,"yyyymmdd")&"|"&TEXT(ROUND(ABS(F10),2),"0.00") | H10: =COUNTIFS(Bank_Import!$G$5:$G$45,G10) | I10: =IF(COUNTIFS($G$5:$G$45,G10)>1,"Possible Duplicate",IF(H10=0,"Unmatched",IF(H10>1,"Possible Duplicate","Matched")))
A11: 46030 | B11: BILLPAY-2202 | C11: Payment - Piedmont Packaging | D11: 0 | E11: 2190 | F11: =D11-E11 | G11: =TEXT(A11,"yyyymmdd")&"|"&TEXT(ROUND(ABS(F11),2),"0.00") | H11: =COUNTIFS(Bank_Import!$G$5:$G$45,G11) | I11: =IF(COUNTIFS($G$5:$G$45,G11)>1,"Possible Duplicate",IF(H11=0,"Unmatched",IF(H11>1,"Possible Duplicate","Matched")))
A12: 46031 | B12: PR-010926 | C12: Payroll Direct Deposit | D12: 0 | E12: 26500 | F12: =D12-E12 | G12: =TEXT(A12,"yyyymmdd")&"|"&TEXT(ROUND(ABS(F12),2),"0.00") | H12: =COUNTIFS(Bank_Import!$G$5:$G$45,G12) | I12: =IF(COUNTIFS($G$5:$G$45,G12)>1,"Possible Duplicate",IF(H12=0,"Unmatched",IF(H12>1,"Possible Duplicate","Matched")))
A13: 46032 | B13: DEP-1004 | C13: Receipt - Coastal Supply | D13: 6100 | E13: 0 | F13: =D13-E13 | G13: =TEXT(A13,"yyyymmdd")&"|"&TEXT(ROUND(ABS(F13),2),"0.00") | H13: =COUNTIFS(Bank_Import!$G$5:$G$45,G13) | I13: =IF(COUNTIFS($G$5:$G$45,G13)>1,"Possible Duplicate",IF(H13=0,"Unmatched",IF(H13>1,"Possible Duplicate","Matched")))
A14: 46033 | B14: BILLPAY-2203 | C14: Payment - Virginia Office Supply | D14: 0 | E14: 745.9 | F14: =D14-E14 | G14: =TEXT(A14,"yyyymmdd")&"|"&TEXT(ROUND(ABS(F14),2),"0.00") | H14: =COUNTIFS(Bank_Import!$G$5:$G$45,G14) | I14: =IF(COUNTIFS($G$5:$G$45,G14)>1,"Possible Duplicate",IF(H14=0,"Unmatched",IF(H14>1,"Possible Duplicate","Matched")))
A15: 46034 | B15: SUB-QBO | C15: QuickBooks Payroll Subscription | D15: 0 | E15: 348 | F15: =D15-E15 | G15: =TEXT(A15,"yyyymmdd")&"|"&TEXT(ROUND(ABS(F15),2),"0.00") | H15: =COUNTIFS(Bank_Import!$G$5:$G$45,G15) | I15: =IF(COUNTIFS($G$5:$G$45,G15)>1,"Possible Duplicate",IF(H15=0,"Unmatched",IF(H15>1,"Possible Duplicate","Matched")))
A16: 46035 | B16: DEP-1005 | C16: Receipt - Metro Equipment | D16: 4900 | E16: 0 | F16: =D16-E16 | G16: =TEXT(A16,"yyyymmdd")&"|"&TEXT(ROUND(ABS(F16),2),"0.00") | H16: =COUNTIFS(Bank_Import!$G$5:$G$45,G16) | I16: =IF(COUNTIFS($G$5:$G$45,G16)>1,"Possible Duplicate",IF(H16=0,"Unmatched",IF(H16>1,"Possible Duplicate","Matched")))
A17: 46036 | B17: BILLPAY-7002 | C17: Payment - Capital Machinery Leasing | D17: 0 | E17: 4160 | F17: =D17-E17 | G17: =TEXT(A17,"yyyymmdd")&"|"&TEXT(ROUND(ABS(F17),2),"0.00") | H17: =COUNTIFS(Bank_Import!$G$5:$G$45,G17) | I17: =IF(COUNTIFS($G$5:$G$45,G17)>1,"Possible Duplicate",IF(H17=0,"Unmatched",IF(H17>1,"Possible Duplicate","Matched")))
A18: 46037 | B18: RENT-JAN | C18: Rent Payment - Fairfax Industrial Park | D18: 0 | E18: 8750 | F18: =D18-E18 | G18: =TEXT(A18,"yyyymmdd")&"|"&TEXT(ROUND(ABS(F18),2),"0.00") | H18: =COUNTIFS(Bank_Import!$G$5:$G$45,G18) | I18: =IF(COUNTIFS($G$5:$G$45,G18)>1,"Possible Duplicate",IF(H18=0,"Unmatched",IF(H18>1,"Possible Duplicate","Matched")))
A19: 46038 | B19: DEP-1006 | C19: Receipt - Old Dominion Components | D19: 7250 | E19: 0 | F19: =D19-E19 | G19: =TEXT(A19,"yyyymmdd")&"|"&TEXT(ROUND(ABS(F19),2),"0.00") | H19: =COUNTIFS(Bank_Import!$G$5:$G$45,G19) | I19: =IF(COUNTIFS($G$5:$G$45,G19)>1,"Possible Duplicate",IF(H19=0,"Unmatched",IF(H19>1,"Possible Duplicate","Matched")))
A20: 46039 | B20: BILLPAY-2204 | C20: Payment - SafetyFirst Supplies | D20: 0 | E20: 1250 | F20: =D20-E20 | G20: =TEXT(A20,"yyyymmdd")&"|"&TEXT(ROUND(ABS(F20),2),"0.00") | H20: =COUNTIFS(Bank_Import!$G$5:$G$45,G20) | I20: =IF(COUNTIFS($G$5:$G$45,G20)>1,"Possible Duplicate",IF(H20=0,"Unmatched",IF(H20>1,"Possible Duplicate","Matched")))
... A34: 46053 | B34: PAYTAX-JAN | C34: Payroll Tax Payment | D34: 0 | E34: 7025 | F34: =D34-E34 | G34: =TEXT(A34,"yyyymmdd")&"|"&TEXT(ROUND(ABS(F34),2),"0.00") | H34: =COUNTIFS(Bank_Import!$G$5:$G$45,G34) | I34: =IF(COUNTIFS($G$5:$G$45,G34)>1,"Possible Duplicate",IF(H34=0,"Unmatched",IF(H34>1,"Possible Duplicate","Matched")))
A35: 46053 | B35: DEP-1013 | C35: Receipt - Late customer deposit | D35: 3250 | E35: 0 | F35: =D35-E35 | G35: =TEXT(A35,"yyyymmdd")&"|"&TEXT(ROUND(ABS(F35),2),"0.00") | H35: =COUNTIFS(Bank_Import!$G$5:$G$45,G35) | I35: =IF(COUNTIFS($G$5:$G$45,G35)>1,"Possible Duplicate",IF(H35=0,"Unmatched",IF(H35>1,"Possible Duplicate","Matched"))) | J35: Deposit in transit
A36: 46053 | B36: BILLPAY-2208 | C36: Payment - Blue Ridge Maintenance | D36: 0 | E36: 2780 | F36: =D36-E36 | G36: =TEXT(A36,"yyyymmdd")&"|"&TEXT(ROUND(ABS(F36),2),"0.00") | H36: =COUNTIFS(Bank_Import!$G$5:$G$45,G36) | I36: =IF(COUNTIFS($G$5:$G$45,G36)>1,"Possible Duplicate",IF(H36=0,"Unmatched",IF(H36>1,"Possible Duplicate","Matched"))) | J36: Outstanding check
A37: 46024 | B37: DEP-1001-DUP | C37: Duplicate receipt - Blue Ridge Retail | D37: 4200 | E37: 0 | F37: =D37-E37 | G37: =TEXT(A37,"yyyymmdd")&"|"&TEXT(ROUND(ABS(F37),2),"0.00") | H37: =COUNTIFS(Bank_Import!$G$5:$G$45,G37) | I37: =IF(COUNTIFS($G$5:$G$45,G37)>1,"Possible Duplicate",IF(H37=0,"Unmatched",IF(H37>1,"Possible Duplicate","Matched"))) | J37: Duplicate entry to investigate

Sheet Reconciliation
A1: Bank Reconciliation Summary
A2: Complete this after reviewing Bank_Import and GL_Import.
A4: Input / Formula | B4: Amount | C4: Student Explanation
A5: Beginning Bank Balance | B5: 84250
A6: Ending Bank Balance per Statement | B6: =B5+SUM(Bank_Import!F5:F36) | C6: From bank statement activity
A8: Add: Deposits in Transit (book receipts not on bank) | B8: =SUMIFS(GL_Import!D5:D45,GL_Import!I5:I45,"Unmatched",GL_Import!D5:D45,">0")
A9: Less: Outstanding Checks/Payments (book payments not on bank) | B9: =SUMIFS(GL_Import!E5:E45,GL_Import!I5:I45,"Unmatched",GL_Import!E5:E45,">0")
A10: Adjusted Bank Balance | B10: =B6+B8-B9
A12: Beginning Book Cash Balance | B12: 84250
A13: Ending Book Balance per GL | B13: =B12+SUM(GL_Import!F5:F45) | C13: From GL cash activity
A14: Add: Bank Deposits/Interest Not Recorded in Books | B14: =SUMIFS(Bank_Import!D5:D45,Bank_Import!I5:I45,"Unmatched",Bank_Import!D5:D45,">0")
A15: Less: Bank Fees/Withdrawals Not Recorded in Books | B15: =SUMIFS(Bank_Import!E5:E45,Bank_Import!I5:I45,"Unmatched",Bank_Import!E5:E45,">0")
A16: Less: Duplicate Book Entries confirmed in Difference_Log (+/-) | B16: 4200 | C16: Investigate rows flagged "Possible Duplicate" in GL_Import. Enter the total book overstatement from confirmed duplicates (sample data: DEP-1001-DUP, $4,200). Use a negative number only if books are understated.
A17: Adjusted Book Balance | B17: =B13+B14-B15-B16
A19: Reconciliation Difference | B19: =B10-B17 | C19: Should be zero after corrections.

Sheet Difference_Log
A1: Difference Log
A2: Document each reconciling item and proposed correction.
A4: Item # | B4: Source | C4: Date | D4: Reference | E4: Issue Type | F4: Amount | G4: Proposed Correction
A5: 1
A6: 2
A7: 3
A8: 4
A9: 5
A10: 6
A11: 7
A12: 8
A13: 9
A14: 10
A15: 11
A16: 12
... A19: 15
