Workbook

Sheet Instructions
A1: Expense Analysis Dashboard
A2: Template for summarizing operating expenses by category, vendor, and month with chart visuals.
A4: Section | B4: Details
A5: Purpose | B5: Template for summarizing operating expenses by category, vendor, and month with chart visuals.
A6: How to Use | B6: 1. Paste expense transactions into Expense_Data. 2. Review Dashboard KPI cells for total expenses and largest categories. 3. Use the category-month summary as a pivot-style expense view. 4. Review the vendor summary to identify heavy spend vendors. 5. Use filters in the Expense_Data table for detailed review.
A7: Expected Output | B7: • Expense totals by month • Expense totals by category • Vendor spend summary • Charts for management reporting
A8: Student Rule | B8: Use the sample data first. Then replace the sample rows with your assigned company data. Do not overwrite formula cells unless your instructor tells you to.
A9: Skarion Simulation | B9: These templates support the Skarion Manufacturing LLC accounting job simulation and can be used as student handouts.

Sheet Expense_Data
A1: Expense Data
A2: Sample operating expense transactions. Replace rows as needed.
A4: Date | B4: Month | C4: Vendor | D4: Category | E4: Payment Method | F4: Department | G4: Amount | H4: Memo | I4: Review Flag
A5: 46024 | B5: =TEXT(A5,"mmm yyyy") | C5: Virginia Office Supply | D5: Office Supplies | E5: Credit Card | F5: Admin | G5: 312.4 | H5: Printer paper and toner | I5: =IF(G5>2000,"Review > $2,000","")
A6: 46025 | B6: =TEXT(A6,"mmm yyyy") | C6: Dominion Energy | D6: Utilities | E6: ACH | F6: Operations | G6: 1280.75 | H6: Electricity | I6: =IF(G6>2000,"Review > $2,000","")
A7: 46027 | B7: =TEXT(A7,"mmm yyyy") | C7: Fairfax Industrial Park | D7: Rent | E7: ACH | F7: Operations | G7: 8750 | H7: Monthly rent | I7: =IF(G7>2000,"Review > $2,000","")
A8: 46028 | B8: =TEXT(A8,"mmm yyyy") | C8: QuickBooks Payroll | D8: Software | E8: ACH | F8: Accounting | G8: 348 | H8: Payroll subscription | I8: =IF(G8>2000,"Review > $2,000","")
A9: 46030 | B9: =TEXT(A9,"mmm yyyy") | C9: DataSafe Cloud Backup | D9: Software | E9: Credit Card | F9: IT | G9: 425 | H9: Cloud backup | I9: =IF(G9>2000,"Review > $2,000","")
A10: 46031 | B10: =TEXT(A10,"mmm yyyy") | C10: Ridgeway Freight Services | D10: Freight | E10: Check | F10: Operations | G10: 1885.25 | H10: Outbound freight | I10: =IF(G10>2000,"Review > $2,000","")
A11: 46032 | B11: =TEXT(A11,"mmm yyyy") | C11: Skyline Janitorial | D11: Facilities | E11: Check | F11: Operations | G11: 685 | H11: Cleaning service | I11: =IF(G11>2000,"Review > $2,000","")
A12: 46034 | B12: =TEXT(A12,"mmm yyyy") | C12: SafetyFirst Supplies | D12: Safety Supplies | E12: Check | F12: Operations | G12: 1250 | H12: Gloves and PPE | I12: =IF(G12>2000,"Review > $2,000","")
A13: 46037 | B13: =TEXT(A13,"mmm yyyy") | C13: Hampton Roads Insurance | D13: Insurance | E13: ACH | F13: Admin | G13: 1950 | H13: General liability premium | I13: =IF(G13>2000,"Review > $2,000","")
A14: 46040 | B14: =TEXT(A14,"mmm yyyy") | C14: Richmond Tax Advisors | D14: Professional Fees | E14: ACH | F14: Accounting | G14: 1200 | H14: Bookkeeping support | I14: =IF(G14>2000,"Review > $2,000","")
A15: 46042 | B15: =TEXT(A15,"mmm yyyy") | C15: Microsoft 365 | D15: Software | E15: Credit Card | F15: Admin | G15: 265 | H15: Office subscription | I15: =IF(G15>2000,"Review > $2,000","")
A16: 46043 | B16: =TEXT(A16,"mmm yyyy") | C16: FuelFleet Cards | D16: Vehicle Expense | E16: Credit Card | F16: Operations | G16: 540.35 | H16: Delivery fuel | I16: =IF(G16>2000,"Review > $2,000","")
... A49: 46108 | B49: =TEXT(A49,"mmm yyyy") | C49: Verizon Business | D49: Telecom | E49: ACH | F49: Admin | G49: 310.5 | H49: Phone and internet | I49: =IF(G49>2000,"Review > $2,000","")

Sheet Dashboard
A1: Expense Analysis Dashboard
A2: Formula-based pivot-style summary for management review.
A4: KPI | B4: Amount
A5: Total Expenses | B5: =SUM(Expense_Data!G5:G49)
A6: Average Transaction | B6: =AVERAGE(Expense_Data!G5:G49)
A7: Transactions > $2,000 | B7: =COUNTIF(Expense_Data!I5:I49,"Review > $2,000")
A8: Largest Single Expense | B8: =MAX(Expense_Data!G5:G49)
A11: Category | B11: Jan 2026 | C11: Feb 2026 | D11: Mar 2026 | E11: Total | G11: Vendor | H11: Total Spend
A12: Rent | B12: =SUMIFS(Expense_Data!$G$5:$G$49,Expense_Data!$D$5:$D$49,$A12,Expense_Data!$B$5:$B$49,B$11) | C12: =SUMIFS(Expense_Data!$G$5:$G$49,Expense_Data!$D$5:$D$49,$A12,Expense_Data!$B$5:$B$49,C$11) | D12: =SUMIFS(Expense_Data!$G$5:$G$49,Expense_Data!$D$5:$D$49,$A12,Expense_Data!$B$5:$B$49,D$11) | E12: =SUM(B12:D12) | G12: Fairfax Industrial Park | H12: =SUMIFS(Expense_Data!$G$5:$G$49,Expense_Data!$C$5:$C$49,G12)
A13: Utilities | B13: =SUMIFS(Expense_Data!$G$5:$G$49,Expense_Data!$D$5:$D$49,$A13,Expense_Data!$B$5:$B$49,B$11) | C13: =SUMIFS(Expense_Data!$G$5:$G$49,Expense_Data!$D$5:$D$49,$A13,Expense_Data!$B$5:$B$49,C$11) | D13: =SUMIFS(Expense_Data!$G$5:$G$49,Expense_Data!$D$5:$D$49,$A13,Expense_Data!$B$5:$B$49,D$11) | E13: =SUM(B13:D13) | G13: Dominion Energy | H13: =SUMIFS(Expense_Data!$G$5:$G$49,Expense_Data!$C$5:$C$49,G13)
A14: Software | B14: =SUMIFS(Expense_Data!$G$5:$G$49,Expense_Data!$D$5:$D$49,$A14,Expense_Data!$B$5:$B$49,B$11) | C14: =SUMIFS(Expense_Data!$G$5:$G$49,Expense_Data!$D$5:$D$49,$A14,Expense_Data!$B$5:$B$49,C$11) | D14: =SUMIFS(Expense_Data!$G$5:$G$49,Expense_Data!$D$5:$D$49,$A14,Expense_Data!$B$5:$B$49,D$11) | E14: =SUM(B14:D14) | G14: Ridgeway Freight Services | H14: =SUMIFS(Expense_Data!$G$5:$G$49,Expense_Data!$C$5:$C$49,G14)
A15: Freight | B15: =SUMIFS(Expense_Data!$G$5:$G$49,Expense_Data!$D$5:$D$49,$A15,Expense_Data!$B$5:$B$49,B$11) | C15: =SUMIFS(Expense_Data!$G$5:$G$49,Expense_Data!$D$5:$D$49,$A15,Expense_Data!$B$5:$B$49,C$11) | D15: =SUMIFS(Expense_Data!$G$5:$G$49,Expense_Data!$D$5:$D$49,$A15,Expense_Data!$B$5:$B$49,D$11) | E15: =SUM(B15:D15) | G15: Richmond Tax Advisors | H15: =SUMIFS(Expense_Data!$G$5:$G$49,Expense_Data!$C$5:$C$49,G15)
A16: Facilities | B16: =SUMIFS(Expense_Data!$G$5:$G$49,Expense_Data!$D$5:$D$49,$A16,Expense_Data!$B$5:$B$49,B$11) | C16: =SUMIFS(Expense_Data!$G$5:$G$49,Expense_Data!$D$5:$D$49,$A16,Expense_Data!$B$5:$B$49,C$11) | D16: =SUMIFS(Expense_Data!$G$5:$G$49,Expense_Data!$D$5:$D$49,$A16,Expense_Data!$B$5:$B$49,D$11) | E16: =SUM(B16:D16) | G16: Hampton Roads Insurance | H16: =SUMIFS(Expense_Data!$G$5:$G$49,Expense_Data!$C$5:$C$49,G16)
A17: Safety Supplies | B17: =SUMIFS(Expense_Data!$G$5:$G$49,Expense_Data!$D$5:$D$49,$A17,Expense_Data!$B$5:$B$49,B$11) | C17: =SUMIFS(Expense_Data!$G$5:$G$49,Expense_Data!$D$5:$D$49,$A17,Expense_Data!$B$5:$B$49,C$11) | D17: =SUMIFS(Expense_Data!$G$5:$G$49,Expense_Data!$D$5:$D$49,$A17,Expense_Data!$B$5:$B$49,D$11) | E17: =SUM(B17:D17) | G17: Blue Ridge Maintenance | H17: =SUMIFS(Expense_Data!$G$5:$G$49,Expense_Data!$C$5:$C$49,G17)
A18: Insurance | B18: =SUMIFS(Expense_Data!$G$5:$G$49,Expense_Data!$D$5:$D$49,$A18,Expense_Data!$B$5:$B$49,B$11) | C18: =SUMIFS(Expense_Data!$G$5:$G$49,Expense_Data!$D$5:$D$49,$A18,Expense_Data!$B$5:$B$49,C$11) | D18: =SUMIFS(Expense_Data!$G$5:$G$49,Expense_Data!$D$5:$D$49,$A18,Expense_Data!$B$5:$B$49,D$11) | E18: =SUM(B18:D18) | G18: SafetyFirst Supplies | H18: =SUMIFS(Expense_Data!$G$5:$G$49,Expense_Data!$C$5:$C$49,G18)
A19: Professional Fees | B19: =SUMIFS(Expense_Data!$G$5:$G$49,Expense_Data!$D$5:$D$49,$A19,Expense_Data!$B$5:$B$49,B$11) | C19: =SUMIFS(Expense_Data!$G$5:$G$49,Expense_Data!$D$5:$D$49,$A19,Expense_Data!$B$5:$B$49,C$11) | D19: =SUMIFS(Expense_Data!$G$5:$G$49,Expense_Data!$D$5:$D$49,$A19,Expense_Data!$B$5:$B$49,D$11) | E19: =SUM(B19:D19) | G19: DataSafe Cloud Backup | H19: =SUMIFS(Expense_Data!$G$5:$G$49,Expense_Data!$C$5:$C$49,G19)
A20: Office Supplies | B20: =SUMIFS(Expense_Data!$G$5:$G$49,Expense_Data!$D$5:$D$49,$A20,Expense_Data!$B$5:$B$49,B$11) | C20: =SUMIFS(Expense_Data!$G$5:$G$49,Expense_Data!$D$5:$D$49,$A20,Expense_Data!$B$5:$B$49,C$11) | D20: =SUMIFS(Expense_Data!$G$5:$G$49,Expense_Data!$D$5:$D$49,$A20,Expense_Data!$B$5:$B$49,D$11) | E20: =SUM(B20:D20) | G20: QuickBooks Payroll | H20: =SUMIFS(Expense_Data!$G$5:$G$49,Expense_Data!$C$5:$C$49,G20)
A21: Vehicle Expense | B21: =SUMIFS(Expense_Data!$G$5:$G$49,Expense_Data!$D$5:$D$49,$A21,Expense_Data!$B$5:$B$49,B$11) | C21: =SUMIFS(Expense_Data!$G$5:$G$49,Expense_Data!$D$5:$D$49,$A21,Expense_Data!$B$5:$B$49,C$11) | D21: =SUMIFS(Expense_Data!$G$5:$G$49,Expense_Data!$D$5:$D$49,$A21,Expense_Data!$B$5:$B$49,D$11) | E21: =SUM(B21:D21) | G21: Verizon Business | H21: =SUMIFS(Expense_Data!$G$5:$G$49,Expense_Data!$C$5:$C$49,G21)
A22: Repairs & Maintenance | B22: =SUMIFS(Expense_Data!$G$5:$G$49,Expense_Data!$D$5:$D$49,$A22,Expense_Data!$B$5:$B$49,B$11) | C22: =SUMIFS(Expense_Data!$G$5:$G$49,Expense_Data!$D$5:$D$49,$A22,Expense_Data!$B$5:$B$49,C$11) | D22: =SUMIFS(Expense_Data!$G$5:$G$49,Expense_Data!$D$5:$D$49,$A22,Expense_Data!$B$5:$B$49,D$11) | E22: =SUM(B22:D22) | G22: Virginia Office Supply | H22: =SUMIFS(Expense_Data!$G$5:$G$49,Expense_Data!$C$5:$C$49,G22)
A23: Recruiting | B23: =SUMIFS(Expense_Data!$G$5:$G$49,Expense_Data!$D$5:$D$49,$A23,Expense_Data!$B$5:$B$49,B$11) | C23: =SUMIFS(Expense_Data!$G$5:$G$49,Expense_Data!$D$5:$D$49,$A23,Expense_Data!$B$5:$B$49,C$11) | D23: =SUMIFS(Expense_Data!$G$5:$G$49,Expense_Data!$D$5:$D$49,$A23,Expense_Data!$B$5:$B$49,D$11) | E23: =SUM(B23:D23) | G23: FuelFleet Cards | H23: =SUMIFS(Expense_Data!$G$5:$G$49,Expense_Data!$C$5:$C$49,G23)
A24: Telecom | B24: =SUMIFS(Expense_Data!$G$5:$G$49,Expense_Data!$D$5:$D$49,$A24,Expense_Data!$B$5:$B$49,B$11) | C24: =SUMIFS(Expense_Data!$G$5:$G$49,Expense_Data!$D$5:$D$49,$A24,Expense_Data!$B$5:$B$49,C$11) | D24: =SUMIFS(Expense_Data!$G$5:$G$49,Expense_Data!$D$5:$D$49,$A24,Expense_Data!$B$5:$B$49,D$11) | E24: =SUM(B24:D24) | G24: Microsoft 365 | H24: =SUMIFS(Expense_Data!$G$5:$G$49,Expense_Data!$C$5:$C$49,G24)
A25: Grand Total | B25: =SUM(B12:B24) | C25: =SUM(C12:C24) | D25: =SUM(D12:D24) | E25: =SUM(E12:E24) | G25: Skyline Janitorial | H25: =SUMIFS(Expense_Data!$G$5:$G$49,Expense_Data!$C$5:$C$49,G25)
G26: LinkedIn Jobs | H26: =SUMIFS(Expense_Data!$G$5:$G$49,Expense_Data!$C$5:$C$49,G26)
G27: Indeed | H27: =SUMIFS(Expense_Data!$G$5:$G$49,Expense_Data!$C$5:$C$49,G27)
